Workbook

Sheet Lisez-moi
A1: Modèle comptable cashless — grand livre en partie double
A3: Statut | B3: NON NORMATIF. Ce classeur illustre le modèle. La référence exécutable est scenario_reference.json, rejoué contre la base par scenario_reference_test.sql (pgTAP) : en cas d'écart, c'est la base et le scénario rejoué qui font foi.
A4: Version | B4: v3 — casse partagée par contrat (L-OPE-CASSE), caution en mode C (Aminata, rendue) et D (Jean, acquise), versement final au prestataire. v2 — ajouts : taxe sur frais et commissions (HT/TVA), versements en deux temps avec un échec, colonnes Source et Clé d'idempotence, solde courant par ligne, listes déroulantes, droits nets par partie, dates ordonnées.
A5: Objet | B5: Simuler de bout en bout le grand livre d'un pool de fonds cashless (un événement, une devise) : recharges, ventes, anomalie hors ligne, clôture, frais des 4 niveaux, versements, remboursements, casse.
A6: Scénario | B6: Festival Sons 2026, XOF. 6 festivaliers (dont 1 staff avec crédits offerts), 1 bar interne, 2 commerçants externes, 1 caisse espèces, 3 canaux PSP, cautions sur deux bracelets. Toutes les données sont fictives.
A7: Convention | B7: Chaque transaction (même n° T..) est équilibrée : total débit = total crédit. Comptes Argent = actif ; comptes Droit = ce que le pool doit à chaque partie.
A8: Paramètres | B8: Cellules jaunes à texte bleu : taux, frais, espèces comptées, arrêté de la balance. Tout se recalcule, y compris les versements (calculés sur les soldes).
A9: Plan de comptes | B9: 37 comptes : argent, portefeuilles, commerçants, sous-comptes de l'organisateur, du prestataire et de la plateforme, compte d'attente.
A10: Journal | B10: Toutes les lignes. Montants bleus = saisis (données du scénario), noirs = calculés. Colonne « Équilibre tx » : doit valoir 0 partout.
A11: Grand livre | B11: Mouvements regroupés par compte avec solde cumulé (disposition figée sur les lignes du scénario).
A12: Balance | B12: Balance dynamique arrêtée à la transaction choisie, et contrôles : équilibre, argent = droits, soldes interdits, compte d'attente.
A13: Relevés | B13: Relevés commerçants et festivaliers, et ce que gagne chaque partie (organisateur, prestataire, plateforme).
A14: SYSCOHADA | B14: Correspondance indicative vers la comptabilité légale de l'organisateur (à valider par un expert-comptable).
... A16: Couleurs | B16: Bleu = saisie ; noir = formule ; vert = lien vers une autre feuille ; jaune = hypothèse à ajuster.

Sheet Paramètres
A1: Paramètres de l'événement
A2: Cellules jaunes à texte bleu = hypothèses modifiables. Tout le reste du classeur se recalcule.
A4: Paramètre | B4: Niveau de configuration | C4: Valeur | D4: Commentaire
A5: Devise de l'événement | B5: Événement | C5: XOF | D5: Une devise par événement ; montants en unités mineures (0 décimale en XOF)
A6: Frais PSP Wave | B6: Contrat PSP | C6: 0.01 | D6: Hypothèse d'exemple, à remplacer par le contrat réel
A7: Frais PSP Orange Money | B7: Contrat PSP | C7: 0.015 | D7: Hypothèse d'exemple
A8: Frais PSP carte bancaire | B8: Contrat PSP | C8: 0.025 | D8: Hypothèse d'exemple
A9: Payeur des frais PSP | B9: Événement (psp_fee_bearer) | C9: ORGANIZER | D9: Dans ce modèle : débités sur L-ORG-FPSP
A10: Frais d'activation par bracelet (festivalier) | B10: Événement | C10: 1000 | D10: Payés par le festivalier, perçus par l'organisateur (L-ORG-FFEST). Staff exonéré
A11: Frais de remboursement du solde | B11: Événement (refund_policy) | C11: 500 | D11: Perçus par l'organisateur
A12: Commission Food truck | B12: Participation commerçant | C12: 0.12 | D12: Commerçant externe
A13: Commission Tee-shirts | B13: Participation commerçant | C13: 0.1 | D13: Commerçant externe
A14: Commission Bar de l'organisateur | B14: Participation commerçant | C14: 0 | D14: Commerçant interne : pas de commission
A15: Droit de place Food truck | B15: Participation commerçant | C15: 15000 | D15: Déduit des ventes à la clôture
A16: Droit de place Tee-shirts | B16: Participation commerçant | C16: 10000 | D16: Déduit des ventes à la clôture
A17: Frais prestataire : % des recharges payées | B17: Contrat prestataire–organisateur | C17: 0.03 | D17: Assiette : recharges hors crédits offerts
A18: Frais prestataire : par bracelet activé | B18: Contrat prestataire–organisateur | C18: 500 | D18: Tous les bracelets, staff compris
A19: Nombre de bracelets activés | B19: Calculé | C19: =COUNTA(Entités!A15:A20) -> 6 | D19: Compté dans la liste des festivaliers (onglet Entités)
A20: Redevance plateforme : % des frais du prestataire | B20: Contrat plateforme–prestataire | C20: 0.2 | D20: Prélevée dans le pool (écriture PLATFORM_FEE)
A21: Taxe sur commissions et frais (TVA) | B21: Profil de législation (tax_rules) | C21: 0.18 | D21: Hypothèse : 18 %, taux normal au Sénégal, à confirmer. Tous les frais et commissions sont TTC. Mettre 0 pour désactiver
A22: Part de la casse revenant à l'organisateur | B22: Contrat prestataire–organisateur (breakage_organizer_bps) | C22: 0.8 | D22: Le reste revient au prestataire (L-OPE-CASSE). Hypothèse d'exemple
A23: Caution par bracelet (lots avec caution) | B23: Lot (deposit_amount) | C23: 2000 | D23: Option du lot. Mode C = prélevée sur le solde ; mode D = payée à part. Hypothèse d'exemple
A24: Espèces comptées à la fermeture de la caisse C1 | B24: Saisie de caisse | C24: 36800 | D24: Le théorique (recharges + caution D en espèces) est calculé par le grand livre ; l'écart va en pertes organisateur
A25: Balance arrêtée à la transaction n° (vide = toutes) | B25: Affichage | D25: Saisir par ex. 23 pour voir la situation à la fin du festival, avant la clôture
A26: Transaction de fin effective (calculé) | C26: =IF($C$25="",MAX(Journal!$A$5:$A$500),$C$25) -> 48

Sheet Entités
A1: Entités du scénario
A2: Hiérarchie multi-tenant : plateforme → prestataire → organisateur → événement → commerçants / points de vente ; festivaliers.
A4: Code | B4: Type | C4: Nom (fictif) | D4: Rattachement | E4: Rôle
A5: PLT | B5: Plateforme | C5: Plateforme Cashless | D5: — | E5: Propriétaire du logiciel ; perçoit une redevance sur le prestataire
A6: OPE | B6: Prestataire cashless | C6: Prestataire Sénégal | D6: PLT | E6: Tenant ; fournit terminaux et bracelets ; perçoit ses frais
A7: ORG | B7: Organisateur | C7: Association Festival Sons | D7: OPE | E7: Émetteur des crédits et détenteur des fonds (compte cantonné)
A8: EVT | B8: Événement | C8: Festival Sons 2026 (11–13 déc.) | D8: ORG | E8: Devise XOF ; portefeuilles par événement (wallet_scope = EVENT)
A9: BAR | B9: Commerçant interne | C9: Bar de l'organisateur | D9: ORG / EVT | E9: Ventes reversées à l'organisateur, sans commission
A10: FOOD | B10: Commerçant externe | C10: Food truck | D10: OPE / EVT | E10: Commission 12 % + droit de place
A11: TEE | B11: Commerçant externe | C11: Vendeur de tee-shirts | D11: OPE / EVT | E11: Commission 10 % + droit de place
A12: C1 | B12: Caisse de recharge | C12: Guichet entrée | D12: EVT | E12: Recharges en espèces
A13: Festivaliers (un portefeuille chacun)
A14: Portefeuille | B14: Nom | C14: Compte crédits payés | D14: Compte crédits offerts | E14: Profil
A15: W01 | B15: Awa | C15: L-WAL-W01-P | D15: — | E15: Recharge Wave ; solde non réclamé → casse
A16: W02 | B16: Moussa | C16: L-WAL-W02-P | D16: — | E16: Recharge Orange Money ; demande un remboursement
A17: W03 | B17: Fatou | C17: L-WAL-W03-P | D17: — | E17: Recharge par carte ; demande un remboursement
A18: W04 | B18: Jean | C18: L-WAL-W04-P | D18: — | E18: Espèces ; vente annulée ; bracelet cloné (anomalie hors ligne)
A19: W05 | B19: Aminata | C19: L-WAL-W05-P | D19: — | E19: Espèces ; solde non réclamé → casse
A20: W06 | B20: Ibou (staff) | C20: — | D20: L-WAL-W06-X | E20: 6 000 de crédits offerts, non remboursables ; 1 000 non utilisés expirent

Sheet Plan de comptes
A1: Plan de comptes du grand livre (pool de l'événement)
A2: Argent = actif (solde normal débiteur). Droit = ce que le pool doit à une partie (solde normal créditeur).
A4: Code | B4: Intitulé | C4: Famille | D4: Titulaire | E4: Solde normal | F4: Négatif permis | G4: purpose (base) | H4: SYSCOHADA indicatif (organisateur)
A5: A-PSP-WAVE | B5: Créance sur Wave | C5: Argent | D5: ORG | E5: D | F5: Non | G5: PSP | H5: Créance sur PSP (classe 4) / 585
A6: A-PSP-OM | B6: Créance sur Orange Money | C6: Argent | D6: ORG | E6: D | F6: Non | G6: PSP | H6: Créance sur PSP (classe 4) / 585
A7: A-PSP-CARTE | B7: Créance sur PSP carte | C7: Argent | D7: ORG | E7: D | F7: Non | G7: PSP | H7: Créance sur PSP (classe 4) / 585
A8: A-CAISSE-C1 | B8: Caisse de recharge C1 (espèces) | C8: Argent | D8: ORG | E8: D | F8: Non | G8: CASH_DESK | H8: 571 Caisse
A9: A-TRANSIT | B9: Espèces en transit vers la banque | C9: Argent | D9: ORG | E9: D | F9: Non | G9: CASH_TRANSIT | H9: 585 Virements de fonds
A10: A-BANQUE | B10: Banque — compte cantonné du pool | C10: Argent | D10: ORG | E10: D | F10: Non | G10: BANK | H10: 521 Banques
A11: L-WAL-W01-P | B11: Portefeuille W01 Awa — crédits payés | C11: Droit | D11: W01 | E11: C | F11: Non | G11: WALLET_PAID | H11: 4191 Clients, avances reçues
A12: L-WAL-W02-P | B12: Portefeuille W02 Moussa — crédits payés | C12: Droit | D12: W02 | E12: C | F12: Non | G12: WALLET_PAID | H12: 4191
A13: L-WAL-W03-P | B13: Portefeuille W03 Fatou — crédits payés | C13: Droit | D13: W03 | E13: C | F13: Non | G13: WALLET_PAID | H13: 4191
A14: L-WAL-W04-P | B14: Portefeuille W04 Jean — crédits payés | C14: Droit | D14: W04 | E14: C | F14: Non | G14: WALLET_PAID | H14: 4191
A15: L-WAL-W05-P | B15: Portefeuille W05 Aminata — crédits payés | C15: Droit | D15: W05 | E15: C | F15: Non | G15: WALLET_PAID | H15: 4191
... A41: S-ATTENTE | B41: Compte d'attente — anomalies | C41: Attente | D41: — | E41: D | F41: Oui | G41: SUSPENSE | H41: Compte d'attente ; doit être à 0 à la clôture

Sheet Journal
A1: Journal — toutes les écritures en partie double
A2: Une transaction = plusieurs lignes avec le même n°. Montants bleus = saisis (données du scénario) ; noirs = calculés (frais, soldes, versements).
A4: N° tx | B4: Date / heure | C4: Type d'opération | D4: Nature de ligne | E4: Libellé | F4: Compte | G4: Intitulé du compte | H4: Débit (XOF) | I4: Crédit (XOF) | J4: Titulaire | K4: Équilibre tx | L4: Source | M4: Clé d'idempotence | N4: Solde du compte après la ligne (D − C)
A5: 1 | B5: 46357.425 | C5: Recharge | D5: Recharge | E5: Recharge WAVE — Awa (prévente en ligne) | F5: A-PSP-WAVE | G5: =IFERROR(INDEX('Plan de comptes'!$B$5:$B$41,MATCH(F5,'Plan de comptes'!$A$5:$A$41,0)),"COMPTE INCONNU") -> Créance sur Wave | H5: 20000 | J5: =IFERROR(INDEX('Plan de comptes'!$D$5:$D$41,MATCH(F5,'Plan de comptes'!$A$5:$A$41,0)),"?") -> ORG | K5: =SUMIFS($H$5:$H$500,$A$5:$A$500,A5)-SUMIFS($I$5:$I$500,$A$5:$A$500,A5) -> 0 | L5: PSP_WEBHOOK | M5: wave:WV-88121 | N5: =SUMIFS($H$5:H5,$F$5:F5,F5)-SUMIFS($I$5:I5,$F$5:F5,F5) -> 20000
A6: 1 | B6: 46357.425 | C6: Recharge | D6: Recharge | E6: Recharge WAVE — Awa (prévente en ligne) | F6: L-WAL-W01-P | G6: =IFERROR(INDEX('Plan de comptes'!$B$5:$B$41,MATCH(F6,'Plan de comptes'!$A$5:$A$41,0)),"COMPTE INCONNU") -> Portefeuille W01 Awa — crédits payés | I6: =H5 -> 20000 | J6: =IFERROR(INDEX('Plan de comptes'!$D$5:$D$41,MATCH(F6,'Plan de comptes'!$A$5:$A$41,0)),"?") -> W01 | K6: =SUMIFS($H$5:$H$500,$A$5:$A$500,A6)-SUMIFS($I$5:$I$500,$A$5:$A$500,A6) -> 0 | L6: PSP_WEBHOOK | M6: wave:WV-88121 | N6: =SUMIFS($H$5:H6,$F$5:F6,F6)-SUMIFS($I$5:I6,$F$5:F6,F6) -> -20000
A7: 1 | B7: 46357.425 | C7: Recharge | D7: Frais PSP | E7: Commission WAVE supportée par l'organisateur | F7: L-ORG-FPSP | G7: =IFERROR(INDEX('Plan de comptes'!$B$5:$B$41,MATCH(F7,'Plan de comptes'!$A$5:$A$41,0)),"COMPTE INCONNU") -> Organisateur — frais PSP supportés | H7: =ROUND(H5*Paramètres!$C$6,0) -> 200 | J7: =IFERROR(INDEX('Plan de comptes'!$D$5:$D$41,MATCH(F7,'Plan de comptes'!$A$5:$A$41,0)),"?") -> ORG | K7: =SUMIFS($H$5:$H$500,$A$5:$A$500,A7)-SUMIFS($I$5:$I$500,$A$5:$A$500,A7) -> 0 | L7: PSP_WEBHOOK | M7: wave:WV-88121 | N7: =SUMIFS($H$5:H7,$F$5:F7,F7)-SUMIFS($I$5:I7,$F$5:F7,F7) -> 200
A8: 1 | B8: 46357.425 | C8: Recharge | D8: Frais PSP | E8: Commission WAVE déduite du versement | F8: A-PSP-WAVE | G8: =IFERROR(INDEX('Plan de comptes'!$B$5:$B$41,MATCH(F8,'Plan de comptes'!$A$5:$A$41,0)),"COMPTE INCONNU") -> Créance sur Wave | I8: =H7 -> 200 | J8: =IFERROR(INDEX('Plan de comptes'!$D$5:$D$41,MATCH(F8,'Plan de comptes'!$A$5:$A$41,0)),"?") -> ORG | K8: =SUMIFS($H$5:$H$500,$A$5:$A$500,A8)-SUMIFS($I$5:$I$500,$A$5:$A$500,A8) -> 0 | L8: PSP_WEBHOOK | M8: wave:WV-88121 | N8: =SUMIFS($H$5:H8,$F$5:F8,F8)-SUMIFS($I$5:I8,$F$5:F8,F8) -> 19800
A9: 2 | B9: 46367.712 | C9: Recharge | D9: Recharge | E9: Recharge OM — Moussa | F9: A-PSP-OM | G9: =IFERROR(INDEX('Plan de comptes'!$B$5:$B$41,MATCH(F9,'Plan de comptes'!$A$5:$A$41,0)),"COMPTE INCONNU") -> Créance sur Orange Money | H9: 15000 | J9: =IFERROR(INDEX('Plan de comptes'!$D$5:$D$41,MATCH(F9,'Plan de comptes'!$A$5:$A$41,0)),"?") -> ORG | K9: =SUMIFS($H$5:$H$500,$A$5:$A$500,A9)-SUMIFS($I$5:$I$500,$A$5:$A$500,A9) -> 0 | L9: PSP_WEBHOOK | M9: om:OM-55310 | N9: =SUMIFS($H$5:H9,$F$5:F9,F9)-SUMIFS($I$5:I9,$F$5:F9,F9) -> 15000
A10: 2 | B10: 46367.712 | C10: Recharge | D10: Recharge | E10: Recharge OM — Moussa | F10: L-WAL-W02-P | G10: =IFERROR(INDEX('Plan de comptes'!$B$5:$B$41,MATCH(F10,'Plan de comptes'!$A$5:$A$41,0)),"COMPTE INCONNU") -> Portefeuille W02 Moussa — crédits payés | I10: =H9 -> 15000 | J10: =IFERROR(INDEX('Plan de comptes'!$D$5:$D$41,MATCH(F10,'Plan de comptes'!$A$5:$A$41,0)),"?") -> W02 | K10: =SUMIFS($H$5:$H$500,$A$5:$A$500,A10)-SUMIFS($I$5:$I$500,$A$5:$A$500,A10) -> 0 | L10: PSP_WEBHOOK | M10: om:OM-55310 | N10: =SUMIFS($H$5:H10,$F$5:F10,F10)-SUMIFS($I$5:I10,$F$5:F10,F10) -> -15000
A11: 2 | B11: 46367.712 | C11: Recharge | D11: Frais PSP | E11: Commission OM supportée par l'organisateur | F11: L-ORG-FPSP | G11: =IFERROR(INDEX('Plan de comptes'!$B$5:$B$41,MATCH(F11,'Plan de comptes'!$A$5:$A$41,0)),"COMPTE INCONNU") -> Organisateur — frais PSP supportés | H11: =ROUND(H9*Paramètres!$C$7,0) -> 225 | J11: =IFERROR(INDEX('Plan de comptes'!$D$5:$D$41,MATCH(F11,'Plan de comptes'!$A$5:$A$41,0)),"?") -> ORG | K11: =SUMIFS($H$5:$H$500,$A$5:$A$500,A11)-SUMIFS($I$5:$I$500,$A$5:$A$500,A11) -> 0 | L11: PSP_WEBHOOK | M11: om:OM-55310 | N11: =SUMIFS($H$5:H11,$F$5:F11,F11)-SUMIFS($I$5:I11,$F$5:F11,F11) -> 425
A12: 2 | B12: 46367.712 | C12: Recharge | D12: Frais PSP | E12: Commission OM déduite du versement | F12: A-PSP-OM | G12: =IFERROR(INDEX('Plan de comptes'!$B$5:$B$41,MATCH(F12,'Plan de comptes'!$A$5:$A$41,0)),"COMPTE INCONNU") -> Créance sur Orange Money | I12: =H11 -> 225 | J12: =IFERROR(INDEX('Plan de comptes'!$D$5:$D$41,MATCH(F12,'Plan de comptes'!$A$5:$A$41,0)),"?") -> ORG | K12: =SUMIFS($H$5:$H$500,$A$5:$A$500,A12)-SUMIFS($I$5:$I$500,$A$5:$A$500,A12) -> 0 | L12: PSP_WEBHOOK | M12: om:OM-55310 | N12: =SUMIFS($H$5:H12,$F$5:F12,F12)-SUMIFS($I$5:I12,$F$5:F12,F12) -> 14775
A13: 3 | B13: 46367.736 | C13: Recharge | D13: Recharge | E13: Recharge CARTE — Fatou | F13: A-PSP-CARTE | G13: =IFERROR(INDEX('Plan de comptes'!$B$5:$B$41,MATCH(F13,'Plan de comptes'!$A$5:$A$41,0)),"COMPTE INCONNU") -> Créance sur PSP carte | H13: 30000 | J13: =IFERROR(INDEX('Plan de comptes'!$D$5:$D$41,MATCH(F13,'Plan de comptes'!$A$5:$A$41,0)),"?") -> ORG | K13: =SUMIFS($H$5:$H$500,$A$5:$A$500,A13)-SUMIFS($I$5:$I$500,$A$5:$A$500,A13) -> 0 | L13: PSP_WEBHOOK | M13: psp:CB-10492 | N13: =SUMIFS($H$5:H13,$F$5:F13,F13)-SUMIFS($I$5:I13,$F$5:F13,F13) -> 30000
A14: 3 | B14: 46367.736 | C14: Recharge | D14: Recharge | E14: Recharge CARTE — Fatou | F14: L-WAL-W03-P | G14: =IFERROR(INDEX('Plan de comptes'!$B$5:$B$41,MATCH(F14,'Plan de comptes'!$A$5:$A$41,0)),"COMPTE INCONNU") -> Portefeuille W03 Fatou — crédits payés | I14: =H13 -> 30000 | J14: =IFERROR(INDEX('Plan de comptes'!$D$5:$D$41,MATCH(F14,'Plan de comptes'!$A$5:$A$41,0)),"?") -> W03 | K14: =SUMIFS($H$5:$H$500,$A$5:$A$500,A14)-SUMIFS($I$5:$I$500,$A$5:$A$500,A14) -> 0 | L14: PSP_WEBHOOK | M14: psp:CB-10492 | N14: =SUMIFS($H$5:H14,$F$5:F14,F14)-SUMIFS($I$5:I14,$F$5:F14,F14) -> -30000
A15: 3 | B15: 46367.736 | C15: Recharge | D15: Frais PSP | E15: Commission CARTE supportée par l'organisateur | F15: L-ORG-FPSP | G15: =IFERROR(INDEX('Plan de comptes'!$B$5:$B$41,MATCH(F15,'Plan de comptes'!$A$5:$A$41,0)),"COMPTE INCONNU") -> Organisateur — frais PSP supportés | H15: =ROUND(H13*Paramètres!$C$8,0) -> 750 | J15: =IFERROR(INDEX('Plan de comptes'!$D$5:$D$41,MATCH(F15,'Plan de comptes'!$A$5:$A$41,0)),"?") -> ORG | K15: =SUMIFS($H$5:$H$500,$A$5:$A$500,A15)-SUMIFS($I$5:$I$500,$A$5:$A$500,A15) -> 0 | L15: PSP_WEBHOOK | M15: psp:CB-10492 | N15: =SUMIFS($H$5:H15,$F$5:F15,F15)-SUMIFS($I$5:I15,$F$5:F15,F15) -> 1175
A16: 3 | B16: 46367.736 | C16: Recharge | D16: Frais PSP | E16: Commission CARTE déduite du versement | F16: A-PSP-CARTE | G16: =IFERROR(INDEX('Plan de comptes'!$B$5:$B$41,MATCH(F16,'Plan de comptes'!$A$5:$A$41,0)),"COMPTE INCONNU") -> Créance sur PSP carte | I16: =H15 -> 750 | J16: =IFERROR(INDEX('Plan de comptes'!$D$5:$D$41,MATCH(F16,'Plan de comptes'!$A$5:$A$41,0)),"?") -> ORG | K16: =SUMIFS($H$5:$H$500,$A$5:$A$500,A16)-SUMIFS($I$5:$I$500,$A$5:$A$500,A16) -> 0 | L16: PSP_WEBHOOK | M16: psp:CB-10492 | N16: =SUMIFS($H$5:H16,$F$5:F16,F16)-SUMIFS($I$5:I16,$F$5:F16,F16) -> 29250
A17: 4 | B17: 46367.751 | C17: Recharge espèces | D17: Recharge | E17: Recharge espèces caisse C1 — Jean | F17: A-CAISSE-C1 | G17: =IFERROR(INDEX('Plan de comptes'!$B$5:$B$41,MATCH(F17,'Plan de comptes'!$A$5:$A$41,0)),"COMPTE INCONNU") -> Caisse de recharge C1 (espèces) | H17: 10000 | J17: =IFERROR(INDEX('Plan de comptes'!$D$5:$D$41,MATCH(F17,'Plan de comptes'!$A$5:$A$41,0)),"?") -> ORG | K17: =SUMIFS($H$5:$H$500,$A$5:$A$500,A17)-SUMIFS($I$5:$I$500,$A$5:$A$500,A17) -> 0 | L17: ONLINE | M17: C1-TPE:0001 | N17: =SUMIFS($H$5:H17,$F$5:F17,F17)-SUMIFS($I$5:I17,$F$5:F17,F17) -> 10000
A18: 4 | B18: 46367.751 | C18: Recharge espèces | D18: Recharge | E18: Recharge espèces caisse C1 — Jean | F18: L-WAL-W04-P | G18: =IFERROR(INDEX('Plan de comptes'!$B$5:$B$41,MATCH(F18,'Plan de comptes'!$A$5:$A$41,0)),"COMPTE INCONNU") -> Portefeuille W04 Jean — crédits payés | I18: =H17 -> 10000 | J18: =IFERROR(INDEX('Plan de comptes'!$D$5:$D$41,MATCH(F18,'Plan de comptes'!$A$5:$A$41,0)),"?") -> W04 | K18: =SUMIFS($H$5:$H$500,$A$5:$A$500,A18)-SUMIFS($I$5:$I$500,$A$5:$A$500,A18) -> 0 | L18: ONLINE | M18: C1-TPE:0001 | N18: =SUMIFS($H$5:H18,$F$5:F18,F18)-SUMIFS($I$5:I18,$F$5:F18,F18) -> -10000
A19: 5 | B19: 46367.752 | C19: Caution | D19: Caution | E19: Caution bracelet payée en espèces (mode D) — Jean | F19: A-CAISSE-C1 | G19: =IFERROR(INDEX('Plan de comptes'!$B$5:$B$41,MATCH(F19,'Plan de comptes'!$A$5:$A$41,0)),"COMPTE INCONNU") -> Caisse de recharge C1 (espèces) | H19: =Paramètres!$C$23 -> 2000 | J19: =IFERROR(INDEX('Plan de comptes'!$D$5:$D$41,MATCH(F19,'Plan de comptes'!$A$5:$A$41,0)),"?") -> ORG | K19: =SUMIFS($H$5:$H$500,$A$5:$A$500,A19)-SUMIFS($I$5:$I$500,$A$5:$A$500,A19) -> 0 | L19: ONLINE | M19: deposit:W04:1 | N19: =SUMIFS($H$5:H19,$F$5:F19,F19)-SUMIFS($I$5:I19,$F$5:F19,F19) -> 12000
A20: 5 | B20: 46367.752 | C20: Caution | D20: Caution | E20: Caution détenue pour le bracelet de Jean | F20: L-ORG-CAUTION | G20: =IFERROR(INDEX('Plan de comptes'!$B$5:$B$41,MATCH(F20,'Plan de comptes'!$A$5:$A$41,0)),"COMPTE INCONNU") -> Organisateur — cautions détenues (à rendre) | I20: =H19 -> 2000 | J20: =IFERROR(INDEX('Plan de comptes'!$D$5:$D$41,MATCH(F20,'Plan de comptes'!$A$5:$A$41,0)),"?") -> ORG | K20: =SUMIFS($H$5:$H$500,$A$5:$A$500,A20)-SUMIFS($I$5:$I$500,$A$5:$A$500,A20) -> 0 | L20: ONLINE | M20: deposit:W04:1 | N20: =SUMIFS($H$5:H20,$F$5:F20,F20)-SUMIFS($I$5:I20,$F$5:F20,F20) -> -2000
A21: 6 | B21: 46367.76 | C21: Recharge espèces | D21: Recharge | E21: Recharge espèces caisse C1 — Aminata | F21: A-CAISSE-C1 | G21: =IFERROR(INDEX('Plan de comptes'!$B$5:$B$41,MATCH(F21,'Plan de comptes'!$A$5:$A$41,0)),"COMPTE INCONNU") -> Caisse de recharge C1 (espèces) | H21: 25000 | J21: =IFERROR(INDEX('Plan de comptes'!$D$5:$D$41,MATCH(F21,'Plan de comptes'!$A$5:$A$41,0)),"?") -> ORG | K21: =SUMIFS($H$5:$H$500,$A$5:$A$500,A21)-SUMIFS($I$5:$I$500,$A$5:$A$500,A21) -> 0 | L21: ONLINE | M21: C1-TPE:0002 | N21: =SUMIFS($H$5:H21,$F$5:F21,F21)-SUMIFS($I$5:I21,$F$5:F21,F21) -> 37000
A22: 6 | B22: 46367.76 | C22: Recharge espèces | D22: Recharge | E22: Recharge espèces caisse C1 — Aminata | F22: L-WAL-W05-P | G22: =IFERROR(INDEX('Plan de comptes'!$B$5:$B$41,MATCH(F22,'Plan de comptes'!$A$5:$A$41,0)),"COMPTE INCONNU") -> Portefeuille W05 Aminata — crédits payés | I22: =H21 -> 25000 | J22: =IFERROR(INDEX('Plan de comptes'!$D$5:$D$41,MATCH(F22,'Plan de comptes'!$A$5:$A$41,0)),"?") -> W05 | K22: =SUMIFS($H$5:$H$500,$A$5:$A$500,A22)-SUMIFS($I$5:$I$500,$A$5:$A$500,A22) -> 0 | L22: ONLINE | M22: C1-TPE:0002 | N22: =SUMIFS($H$5:H22,$F$5:F22,F22)-SUMIFS($I$5:I22,$F$5:F22,F22) -> -25000
A23: 7 | B23: 46367.761 | C23: Caution | D23: Caution | E23: Caution prélevée sur le solde (mode C) — Aminata | F23: L-WAL-W05-P | G23: =IFERROR(INDEX('Plan de comptes'!$B$5:$B$41,MATCH(F23,'Plan de comptes'!$A$5:$A$41,0)),"COMPTE INCONNU") -> Portefeuille W05 Aminata — crédits payés | H23: =Paramètres!$C$23 -> 2000 | J23: =IFERROR(INDEX('Plan de comptes'!$D$5:$D$41,MATCH(F23,'Plan de comptes'!$A$5:$A$41,0)),"?") -> W05 | K23: =SUMIFS($H$5:$H$500,$A$5:$A$500,A23)-SUMIFS($I$5:$I$500,$A$5:$A$500,A23) -> 0 | L23: ONLINE | M23: deposit:W05:1 | N23: =SUMIFS($H$5:H23,$F$5:F23,F23)-SUMIFS($I$5:I23,$F$5:F23,F23) -> -23000
A24: 7 | B24: 46367.761 | C24: Caution | D24: Caution | E24: Caution détenue pour le bracelet d'Aminata | F24: L-ORG-CAUTION | G24: =IFERROR(INDEX('Plan de comptes'!$B$5:$B$41,MATCH(F24,'Plan de comptes'!$A$5:$A$41,0)),"COMPTE INCONNU") -> Organisateur — cautions détenues (à rendre) | I24: =H23 -> 2000 | J24: =IFERROR(INDEX('Plan de comptes'!$D$5:$D$41,MATCH(F24,'Plan de comptes'!$A$5:$A$41,0)),"?") -> ORG | K24: =SUMIFS($H$5:$H$500,$A$5:$A$500,A24)-SUMIFS($I$5:$I$500,$A$5:$A$500,A24) -> 0 | L24: ONLINE | M24: deposit:W05:1 | N24: =SUMIFS($H$5:H24,$F$5:F24,F24)-SUMIFS($I$5:I24,$F$5:F24,F24) -> -4000
A25: 8 | B25: 46367.764 | C25: Crédits offerts | D25: Crédit offert | E25: Crédits staff offerts par l'organisateur — Ibou | F25: L-ORG-PROMO | G25: =IFERROR(INDEX('Plan de comptes'!$B$5:$B$41,MATCH(F25,'Plan de comptes'!$A$5:$A$41,0)),"COMPTE INCONNU") -> Organisateur — financement des crédits offerts | H25: 6000 | J25: =IFERROR(INDEX('Plan de comptes'!$D$5:$D$41,MATCH(F25,'Plan de comptes'!$A$5:$A$41,0)),"?") -> ORG | K25: =SUMIFS($H$5:$H$500,$A$5:$A$500,A25)-SUMIFS($I$5:$I$500,$A$5:$A$500,A25) -> 0 | L25: BACKOFFICE | M25: promo:STAFF-2026-014 | N25: =SUMIFS($H$5:H25,$F$5:F25,F25)-SUMIFS($I$5:I25,$F$5:F25,F25) -> 6000
A26: 8 | B26: 46367.764 | C26: Crédits offerts | D26: Crédit offert | E26: Crédits staff offerts par l'organisateur — Ibou | F26: L-WAL-W06-X | G26: =IFERROR(INDEX('Plan de comptes'!$B$5:$B$41,MATCH(F26,'Plan de comptes'!$A$5:$A$41,0)),"COMPTE INCONNU") -> Portefeuille W06 Ibou — crédits offerts | I26: =H25 -> 6000 | J26: =IFERROR(INDEX('Plan de comptes'!$D$5:$D$41,MATCH(F26,'Plan de comptes'!$A$5:$A$41,0)),"?") -> W06 | K26: =SUMIFS($H$5:$H$500,$A$5:$A$500,A26)-SUMIFS($I$5:$I$500,$A$5:$A$500,A26) -> 0 | L26: BACKOFFICE | M26: promo:STAFF-2026-014 | N26: =SUMIFS($H$5:H26,$F$5:F26,F26)-SUMIFS($I$5:I26,$F$5:F26,F26) -> -6000
A27: 9 | B27: 46367.771 | C27: Frais d'activation | D27: Frais festivalier | E27: Frais d'activation bracelet W01 | F27: L-WAL-W01-P | G27: =IFERROR(INDEX('Plan de comptes'!$B$5:$B$41,MATCH(F27,'Plan de comptes'!$A$5:$A$41,0)),"COMPTE INCONNU") -> Portefeuille W01 Awa — crédits payés | H27: =Paramètres!$C$10 -> 1000 | J27: =IFERROR(INDEX('Plan de comptes'!$D$5:$D$41,MATCH(F27,'Plan de comptes'!$A$5:$A$41,0)),"?") -> W01 | K27: =SUMIFS($H$5:$H$500,$A$5:$A$500,A27)-SUMIFS($I$5:$I$500,$A$5:$A$500,A27) -> 0 | L27: BATCH | M27: activation:EVT-2026:lot1 | N27: =SUMIFS($H$5:H27,$F$5:F27,F27)-SUMIFS($I$5:I27,$F$5:F27,F27) -> -19000
A28: 9 | B28: 46367.771 | C28: Frais d'activation | D28: Frais festivalier | E28: Frais d'activation bracelet W02 | F28: L-WAL-W02-P | G28: =IFERROR(INDEX('Plan de comptes'!$B$5:$B$41,MATCH(F28,'Plan de comptes'!$A$5:$A$41,0)),"COMPTE INCONNU") -> Portefeuille W02 Moussa — crédits payés | H28: =Paramètres!$C$10 -> 1000 | J28: =IFERROR(INDEX('Plan de comptes'!$D$5:$D$41,MATCH(F28,'Plan de comptes'!$A$5:$A$41,0)),"?") -> W02 | K28: =SUMIFS($H$5:$H$500,$A$5:$A$500,A28)-SUMIFS($I$5:$I$500,$A$5:$A$500,A28) -> 0 | L28: BATCH | M28: activation:EVT-2026:lot1 | N28: =SUMIFS($H$5:H28,$F$5:F28,F28)-SUMIFS($I$5:I28,$F$5:F28,F28) -> -14000
A29: 9 | B29: 46367.771 | C29: Frais d'activation | D29: Frais festivalier | E29: Frais d'activation bracelet W03 | F29: L-WAL-W03-P | G29: =IFERROR(INDEX('Plan de comptes'!$B$5:$B$41,MATCH(F29,'Plan de comptes'!$A$5:$A$41,0)),"COMPTE INCONNU") -> Portefeuille W03 Fatou — crédits payés | H29: =Paramètres!$C$10 -> 1000 | J29: =IFERROR(INDEX('Plan de comptes'!$D$5:$D$41,MATCH(F29,'Plan de comptes'!$A$5:$A$41,0)),"?") -> W03 | K29: =SUMIFS($H$5:$H$500,$A$5:$A$500,A29)-SUMIFS($I$5:$I$500,$A$5:$A$500,A29) -> 0 | L29: BATCH | M29: activation:EVT-2026:lot1 | N29: =SUMIFS($H$5:H29,$F$5:F29,F29)-SUMIFS($I$5:I29,$F$5:F29,F29) -> -29000
A30: 9 | B30: 46367.771 | C30: Frais d'activation | D30: Frais festivalier | E30: Frais d'activation bracelet W04 | F30: L-WAL-W04-P | G30: =IFERROR(INDEX('Plan de comptes'!$B$5:$B$41,MATCH(F30,'Plan de comptes'!$A$5:$A$41,0)),"COMPTE INCONNU") -> Portefeuille W04 Jean — crédits payés | H30: =Paramètres!$C$10 -> 1000 | J30: =IFERROR(INDEX('Plan de comptes'!$D$5:$D$41,MATCH(F30,'Plan de comptes'!$A$5:$A$41,0)),"?") -> W04 | K30: =SUMIFS($H$5:$H$500,$A$5:$A$500,A30)-SUMIFS($I$5:$I$500,$A$5:$A$500,A30) -> 0 | L30: BATCH | M30: activation:EVT-2026:lot1 | N30: =SUMIFS($H$5:H30,$F$5:F30,F30)-SUMIFS($I$5:I30,$F$5:F30,F30) -> -9000
A31: 9 | B31: 46367.771 | C31: Frais d'activation | D31: Frais festivalier | E31: Frais d'activation bracelet W05 | F31: L-WAL-W05-P | G31: =IFERROR(INDEX('Plan de comptes'!$B$5:$B$41,MATCH(F31,'Plan de comptes'!$A$5:$A$41,0)),"COMPTE INCONNU") -> Portefeuille W05 Aminata — crédits payés | H31: =Paramètres!$C$10 -> 1000 | J31: =IFERROR(INDEX('Plan de comptes'!$D$5:$D$41,MATCH(F31,'Plan de comptes'!$A$5:$A$41,0)),"?") -> W05 | K31: =SUMIFS($H$5:$H$500,$A$5:$A$500,A31)-SUMIFS($I$5:$I$500,$A$5:$A$500,A31) -> 0 | L31: BATCH | M31: activation:EVT-2026:lot1 | N31: =SUMIFS($H$5:H31,$F$5:F31,F31)-SUMIFS($I$5:I31,$F$5:F31,F31) -> -22000
A32: 9 | B32: 46367.771 | C32: Frais d'activation | D32: Frais festivalier | E32: Frais d'activation perçus (5 bracelets) (HT) | F32: L-ORG-FFEST | G32: =IFERROR(INDEX('Plan de comptes'!$B$5:$B$41,MATCH(F32,'Plan de comptes'!$A$5:$A$41,0)),"COMPTE INCONNU") -> Organisateur — frais festivaliers | I32: =SUM(H27:H31)-ROUND(SUM(H27:H31)*Paramètres!$C$21/(1+Paramètres!$C$21),0) -> 4237 | J32: =IFERROR(INDEX('Plan de comptes'!$D$5:$D$41,MATCH(F32,'Plan de comptes'!$A$5:$A$41,0)),"?") -> ORG | K32: =SUMIFS($H$5:$H$500,$A$5:$A$500,A32)-SUMIFS($I$5:$I$500,$A$5:$A$500,A32) -> 0 | L32: BATCH | M32: activation:EVT-2026:lot1 | N32: =SUMIFS($H$5:H32,$F$5:F32,F32)-SUMIFS($I$5:I32,$F$5:F32,F32) -> -4237
A33: 9 | B33: 46367.771 | C33: Frais d'activation | D33: Frais festivalier | E33: Frais d'activation perçus (5 bracelets) (taxe collectée) | F33: L-ORG-TVA | G33: =IFERROR(INDEX('Plan de comptes'!$B$5:$B$41,MATCH(F33,'Plan de comptes'!$A$5:$A$41,0)),"COMPTE INCONNU") -> Organisateur — taxe collectée (à reverser à l'État) | I33: =ROUND(SUM(H27:H31)*Paramètres!$C$21/(1+Paramètres!$C$21),0) -> 763 | J33: =IFERROR(INDEX('Plan de comptes'!$D$5:$D$41,MATCH(F33,'Plan de comptes'!$A$5:$A$41,0)),"?") -> ORG | K33: =SUMIFS($H$5:$H$500,$A$5:$A$500,A33)-SUMIFS($I$5:$I$500,$A$5:$A$500,A33) -> 0 | L33: BATCH | M33: activation:EVT-2026:lot1 | N33: =SUMIFS($H$5:H33,$F$5:F33,F33)-SUMIFS($I$5:I33,$F$5:F33,F33) -> -763
A34: 10 | B34: 46367.799 | C34: Vente | D34: Vente | E34: Achat FOOD — Awa | F34: L-WAL-W01-P | G34: =IFERROR(INDEX('Plan de comptes'!$B$5:$B$41,MATCH(F34,'Plan de comptes'!$A$5:$A$41,0)),"COMPTE INCONNU") -> Portefeuille W01 Awa — crédits payés | H34: 6000 | J34: =IFERROR(INDEX('Plan de comptes'!$D$5:$D$41,MATCH(F34,'Plan de comptes'!$A$5:$A$41,0)),"?") -> W01 | K34: =SUMIFS($H$5:$H$500,$A$5:$A$500,A34)-SUMIFS($I$5:$I$500,$A$5:$A$500,A34) -> 0 | L34: ONLINE | M34: TPE-FOOD-01:0001 | N34: =SUMIFS($H$5:H34,$F$5:F34,F34)-SUMIFS($I$5:I34,$F$5:F34,F34) -> -13000
A35: 10 | B35: 46367.799 | C35: Vente | D35: Vente | E35: Vente FOOD — Awa | F35: L-MCH-FOOD | G35: =IFERROR(INDEX('Plan de comptes'!$B$5:$B$41,MATCH(F35,'Plan de comptes'!$A$5:$A$41,0)),"COMPTE INCONNU") -> Commerçant externe — Food truck | I35: =H34 -> 6000 | J35: =IFERROR(INDEX('Plan de comptes'!$D$5:$D$41,MATCH(F35,'Plan de comptes'!$A$5:$A$41,0)),"?") -> FOOD | K35: =SUMIFS($H$5:$H$500,$A$5:$A$500,A35)-SUMIFS($I$5:$I$500,$A$5:$A$500,A35) -> 0 | L35: ONLINE | M35: TPE-FOOD-01:0001 | N35: =SUMIFS($H$5:H35,$F$5:F35,F35)-SUMIFS($I$5:I35,$F$5:F35,F35) -> -6000
A36: 10 | B36: 46367.799 | C36: Vente | D36: Commission | E36: Commission TTC sur vente FOOD | F36: L-MCH-FOOD | G36: =IFERROR(INDEX('Plan de comptes'!$B$5:$B$41,MATCH(F36,'Plan de comptes'!$A$5:$A$41,0)),"COMPTE INCONNU") -> Commerçant externe — Food truck | H36: =ROUND(I35*Paramètres!$C$12,0) -> 720 | J36: =IFERROR(INDEX('Plan de comptes'!$D$5:$D$41,MATCH(F36,'Plan de comptes'!$A$5:$A$41,0)),"?") -> FOOD | K36: =SUMIFS($H$5:$H$500,$A$5:$A$500,A36)-SUMIFS($I$5:$I$500,$A$5:$A$500,A36) -> 0 | L36: ONLINE | M36: TPE-FOOD-01:0001 | N36: =SUMIFS($H$5:H36,$F$5:F36,F36)-SUMIFS($I$5:I36,$F$5:F36,F36) -> -5280
A37: 10 | B37: 46367.799 | C37: Vente | D37: Commission | E37: Commission sur vente FOOD (HT) | F37: L-ORG-COM | G37: =IFERROR(INDEX('Plan de comptes'!$B$5:$B$41,MATCH(F37,'Plan de comptes'!$A$5:$A$41,0)),"COMPTE INCONNU") -> Organisateur — commissions | I37: =H36-ROUND(H36*Paramètres!$C$21/(1+Paramètres!$C$21),0) -> 610 | J37: =IFERROR(INDEX('Plan de comptes'!$D$5:$D$41,MATCH(F37,'Plan de comptes'!$A$5:$A$41,0)),"?") -> ORG | K37: =SUMIFS($H$5:$H$500,$A$5:$A$500,A37)-SUMIFS($I$5:$I$500,$A$5:$A$500,A37) -> 0 | L37: ONLINE | M37: TPE-FOOD-01:0001 | N37: =SUMIFS($H$5:H37,$F$5:F37,F37)-SUMIFS($I$5:I37,$F$5:F37,F37) -> -610
A38: 10 | B38: 46367.799 | C38: Vente | D38: Commission | E38: Commission sur vente FOOD (taxe collectée) | F38: L-ORG-TVA | G38: =IFERROR(INDEX('Plan de comptes'!$B$5:$B$41,MATCH(F38,'Plan de comptes'!$A$5:$A$41,0)),"COMPTE INCONNU") -> Organisateur — taxe collectée (à reverser à l'État) | I38: =ROUND(H36*Paramètres!$C$21/(1+Paramètres!$C$21),0) -> 110 | J38: =IFERROR(INDEX('Plan de comptes'!$D$5:$D$41,MATCH(F38,'Plan de comptes'!$A$5:$A$41,0)),"?") -> ORG | K38: =SUMIFS($H$5:$H$500,$A$5:$A$500,A38)-SUMIFS($I$5:$I$500,$A$5:$A$500,A38) -> 0 | L38: ONLINE | M38: TPE-FOOD-01:0001 | N38: =SUMIFS($H$5:H38,$F$5:F38,F38)-SUMIFS($I$5:I38,$F$5:F38,F38) -> -873
A39: 11 | B39: 46367.837 | C39: Vente | D39: Vente | E39: Achat BAR — Awa | F39: L-WAL-W01-P | G39: =IFERROR(INDEX('Plan de comptes'!$B$5:$B$41,MATCH(F39,'Plan de comptes'!$A$5:$A$41,0)),"COMPTE INCONNU") -> Portefeuille W01 Awa — crédits payés | H39: 4000 | J39: =IFERROR(INDEX('Plan de comptes'!$D$5:$D$41,MATCH(F39,'Plan de comptes'!$A$5:$A$41,0)),"?") -> W01 | K39: =SUMIFS($H$5:$H$500,$A$5:$A$500,A39)-SUMIFS($I$5:$I$500,$A$5:$A$500,A39) -> 0 | L39: ONLINE | M39: TPE-BAR-01:0001 | N39: =SUMIFS($H$5:H39,$F$5:F39,F39)-SUMIFS($I$5:I39,$F$5:F39,F39) -> -9000
A40: 11 | B40: 46367.837 | C40: Vente | D40: Vente | E40: Vente BAR — Awa | F40: L-MCH-BAR | G40: =IFERROR(INDEX('Plan de comptes'!$B$5:$B$41,MATCH(F40,'Plan de comptes'!$A$5:$A$41,0)),"COMPTE INCONNU") -> Commerçant interne — Bar de l'organisateur | I40: =H39 -> 4000 | J40: =IFERROR(INDEX('Plan de comptes'!$D$5:$D$41,MATCH(F40,'Plan de comptes'!$A$5:$A$41,0)),"?") -> BAR | K40: =SUMIFS($H$5:$H$500,$A$5:$A$500,A40)-SUMIFS($I$5:$I$500,$A$5:$A$500,A40) -> 0 | L40: ONLINE | M40: TPE-BAR-01:0001 | N40: =SUMIFS($H$5:H40,$F$5:F40,F40)-SUMIFS($I$5:I40,$F$5:F40,F40) -> -4000
A41: 12 | B41: 46367.854 | C41: Vente | D41: Vente | E41: Achat TEE — Moussa | F41: L-WAL-W02-P | G41: =IFERROR(INDEX('Plan de comptes'!$B$5:$B$41,MATCH(F41,'Plan de comptes'!$A$5:$A$41,0)),"COMPTE INCONNU") -> Portefeuille W02 Moussa — crédits payés | H41: 12000 | J41: =IFERROR(INDEX('Plan de comptes'!$D$5:$D$41,MATCH(F41,'Plan de comptes'!$A$5:$A$41,0)),"?") -> W02 | K41: =SUMIFS($H$5:$H$500,$A$5:$A$500,A41)-SUMIFS($I$5:$I$500,$A$5:$A$500,A41) -> 0 | L41: ONLINE | M41: TPE-TEE-01:0001 | N41: =SUMIFS($H$5:H41,$F$5:F41,F41)-SUMIFS($I$5:I41,$F$5:F41,F41) -> -2000
A42: 12 | B42: 46367.854 | C42: Vente | D42: Vente | E42: Vente TEE — Moussa | F42: L-MCH-TEE | G42: =IFERROR(INDEX('Plan de comptes'!$B$5:$B$41,MATCH(F42,'Plan de comptes'!$A$5:$A$41,0)),"COMPTE INCONNU") -> Commerçant externe — Tee-shirts | I42: =H41 -> 12000 | J42: =IFERROR(INDEX('Plan de comptes'!$D$5:$D$41,MATCH(F42,'Plan de comptes'!$A$5:$A$41,0)),"?") -> TEE | K42: =SUMIFS($H$5:$H$500,$A$5:$A$500,A42)-SUMIFS($I$5:$I$500,$A$5:$A$500,A42) -> 0 | L42: ONLINE | M42: TPE-TEE-01:0001 | N42: =SUMIFS($H$5:H42,$F$5:F42,F42)-SUMIFS($I$5:I42,$F$5:F42,F42) -> -12000
A43: 12 | B43: 46367.854 | C43: Vente | D43: Commission | E43: Commission TTC sur vente TEE | F43: L-MCH-TEE | G43: =IFERROR(INDEX('Plan de comptes'!$B$5:$B$41,MATCH(F43,'Plan de comptes'!$A$5:$A$41,0)),"COMPTE INCONNU") -> Commerçant externe — Tee-shirts | H43: =ROUND(I42*Paramètres!$C$13,0) -> 1200 | J43: =IFERROR(INDEX('Plan de comptes'!$D$5:$D$41,MATCH(F43,'Plan de comptes'!$A$5:$A$41,0)),"?") -> TEE | K43: =SUMIFS($H$5:$H$500,$A$5:$A$500,A43)-SUMIFS($I$5:$I$500,$A$5:$A$500,A43) -> 0 | L43: ONLINE | M43: TPE-TEE-01:0001 | N43: =SUMIFS($H$5:H43,$F$5:F43,F43)-SUMIFS($I$5:I43,$F$5:F43,F43) -> -10800
A44: 12 | B44: 46367.854 | C44: Vente | D44: Commission | E44: Commission sur vente TEE (HT) | F44: L-ORG-COM | G44: =IFERROR(INDEX('Plan de comptes'!$B$5:$B$41,MATCH(F44,'Plan de comptes'!$A$5:$A$41,0)),"COMPTE INCONNU") -> Organisateur — commissions | I44: =H43-ROUND(H43*Paramètres!$C$21/(1+Paramètres!$C$21),0) -> 1017 | J44: =IFERROR(INDEX('Plan de comptes'!$D$5:$D$41,MATCH(F44,'Plan de comptes'!$A$5:$A$41,0)),"?") -> ORG | K44: =SUMIFS($H$5:$H$500,$A$5:$A$500,A44)-SUMIFS($I$5:$I$500,$A$5:$A$500,A44) -> 0 | L44: ONLINE | M44: TPE-TEE-01:0001 | N44: =SUMIFS($H$5:H44,$F$5:F44,F44)-SUMIFS($I$5:I44,$F$5:F44,F44) -> -1627
A45: 12 | B45: 46367.854 | C45: Vente | D45: Commission | E45: Commission sur vente TEE (taxe collectée) | F45: L-ORG-TVA | G45: =IFERROR(INDEX('Plan de comptes'!$B$5:$B$41,MATCH(F45,'Plan de comptes'!$A$5:$A$41,0)),"COMPTE INCONNU") -> Organisateur — taxe collectée (à reverser à l'État) | I45: =ROUND(H43*Paramètres!$C$21/(1+Paramètres!$C$21),0) -> 183 | J45: =IFERROR(INDEX('Plan de comptes'!$D$5:$D$41,MATCH(F45,'Plan de comptes'!$A$5:$A$41,0)),"?") -> ORG | K45: =SUMIFS($H$5:$H$500,$A$5:$A$500,A45)-SUMIFS($I$5:$I$500,$A$5:$A$500,A45) -> 0 | L45: ONLINE | M45: TPE-TEE-01:0001 | N45: =SUMIFS($H$5:H45,$F$5:F45,F45)-SUMIFS($I$5:I45,$F$5:F45,F45) -> -1056
A46: 13 | B46: 46367.875 | C46: Vente | D46: Vente | E46: Achat FOOD — Fatou | F46: L-WAL-W03-P | G46: =IFERROR(INDEX('Plan de comptes'!$B$5:$B$41,MATCH(F46,'Plan de comptes'!$A$5:$A$41,0)),"COMPTE INCONNU") -> Portefeuille W03 Fatou — crédits payés | H46: 9000 | J46: =IFERROR(INDEX('Plan de comptes'!$D$5:$D$41,MATCH(F46,'Plan de comptes'!$A$5:$A$41,0)),"?") -> W03 | K46: =SUMIFS($H$5:$H$500,$A$5:$A$500,A46)-SUMIFS($I$5:$I$500,$A$5:$A$500,A46) -> 0 | L46: ONLINE | M46: TPE-FOOD-01:0002 | N46: =SUMIFS($H$5:H46,$F$5:F46,F46)-SUMIFS($I$5:I46,$F$5:F46,F46) -> -20000
A47: 13 | B47: 46367.875 | C47: Vente | D47: Vente | E47: Vente FOOD — Fatou | F47: L-MCH-FOOD | G47: =IFERROR(INDEX('Plan de comptes'!$B$5:$B$41,MATCH(F47,'Plan de comptes'!$A$5:$A$41,0)),"COMPTE INCONNU") -> Commerçant externe — Food truck | I47: =H46 -> 9000 | J47: =IFERROR(INDEX('Plan de comptes'!$D$5:$D$41,MATCH(F47,'Plan de comptes'!$A$5:$A$41,0)),"?") -> FOOD | K47: =SUMIFS($H$5:$H$500,$A$5:$A$500,A47)-SUMIFS($I$5:$I$500,$A$5:$A$500,A47) -> 0 | L47: ONLINE | M47: TPE-FOOD-01:0002 | N47: =SUMIFS($H$5:H47,$F$5:F47,F47)-SUMIFS($I$5:I47,$F$5:F47,F47) -> -14280
A48: 13 | B48: 46367.875 | C48: Vente | D48: Commission | E48: Commission TTC sur vente FOOD | F48: L-MCH-FOOD | G48: =IFERROR(INDEX('Plan de comptes'!$B$5:$B$41,MATCH(F48,'Plan de comptes'!$A$5:$A$41,0)),"COMPTE INCONNU") -> Commerçant externe — Food truck | H48: =ROUND(I47*Paramètres!$C$12,0) -> 1080 | J48: =IFERROR(INDEX('Plan de comptes'!$D$5:$D$41,MATCH(F48,'Plan de comptes'!$A$5:$A$41,0)),"?") -> FOOD | K48: =SUMIFS($H$5:$H$500,$A$5:$A$500,A48)-SUMIFS($I$5:$I$500,$A$5:$A$500,A48) -> 0 | L48: ONLINE | M48: TPE-FOOD-01:0002 | N48: =SUMIFS($H$5:H48,$F$5:F48,F48)-SUMIFS($I$5:I48,$F$5:F48,F48) -> -13200
A49: 13 | B49: 46367.875 | C49: Vente | D49: Commission | E49: Commission sur vente FOOD (HT) | F49: L-ORG-COM | G49: =IFERROR(INDEX('Plan de comptes'!$B$5:$B$41,MATCH(F49,'Plan de comptes'!$A$5:$A$41,0)),"COMPTE INCONNU") -> Organisateur — commissions | I49: =H48-ROUND(H48*Paramètres!$C$21/(1+Paramètres!$C$21),0) -> 915 | J49: =IFERROR(INDEX('Plan de comptes'!$D$5:$D$41,MATCH(F49,'Plan de comptes'!$A$5:$A$41,0)),"?") -> ORG | K49: =SUMIFS($H$5:$H$500,$A$5:$A$500,A49)-SUMIFS($I$5:$I$500,$A$5:$A$500,A49) -> 0 | L49: ONLINE | M49: TPE-FOOD-01:0002 | N49: =SUMIFS($H$5:H49,$F$5:F49,F49)-SUMIFS($I$5:I49,$F$5:F49,F49) -> -2542
A50: 13 | B50: 46367.875 | C50: Vente | D50: Commission | E50: Commission sur vente FOOD (taxe collectée) | F50: L-ORG-TVA | G50: =IFERROR(INDEX('Plan de comptes'!$B$5:$B$41,MATCH(F50,'Plan de comptes'!$A$5:$A$41,0)),"COMPTE INCONNU") -> Organisateur — taxe collectée (à reverser à l'État) | I50: =ROUND(H48*Paramètres!$C$21/(1+Paramètres!$C$21),0) -> 165 | J50: =IFERROR(INDEX('Plan de comptes'!$D$5:$D$41,MATCH(F50,'Plan de comptes'!$A$5:$A$41,0)),"?") -> ORG | K50: =SUMIFS($H$5:$H$500,$A$5:$A$500,A50)-SUMIFS($I$5:$I$500,$A$5:$A$500,A50) -> 0 | L50: ONLINE | M50: TPE-FOOD-01:0002 | N50: =SUMIFS($H$5:H50,$F$5:F50,F50)-SUMIFS($I$5:I50,$F$5:F50,F50) -> -1221
A51: 14 | B51: 46367.927 | C51: Vente | D51: Vente | E51: Achat BAR — Fatou | F51: L-WAL-W03-P | G51: =IFERROR(INDEX('Plan de comptes'!$B$5:$B$41,MATCH(F51,'Plan de comptes'!$A$5:$A$41,0)),"COMPTE INCONNU") -> Portefeuille W03 Fatou — crédits payés | H51: 7500 | J51: =IFERROR(INDEX('Plan de comptes'!$D$5:$D$41,MATCH(F51,'Plan de comptes'!$A$5:$A$41,0)),"?") -> W03 | K51: =SUMIFS($H$5:$H$500,$A$5:$A$500,A51)-SUMIFS($I$5:$I$500,$A$5:$A$500,A51) -> 0 | L51: ONLINE | M51: TPE-BAR-01:0002 | N51: =SUMIFS($H$5:H51,$F$5:F51,F51)-SUMIFS($I$5:I51,$F$5:F51,F51) -> -12500
A52: 14 | B52: 46367.927 | C52: Vente | D52: Vente | E52: Vente BAR — Fatou | F52: L-MCH-BAR | G52: =IFERROR(INDEX('Plan de comptes'!$B$5:$B$41,MATCH(F52,'Plan de comptes'!$A$5:$A$41,0)),"COMPTE INCONNU") -> Commerçant interne — Bar de l'organisateur | I52: =H51 -> 7500 | J52: =IFERROR(INDEX('Plan de comptes'!$D$5:$D$41,MATCH(F52,'Plan de comptes'!$A$5:$A$41,0)),"?") -> BAR | K52: =SUMIFS($H$5:$H$500,$A$5:$A$500,A52)-SUMIFS($I$5:$I$500,$A$5:$A$500,A52) -> 0 | L52: ONLINE | M52: TPE-BAR-01:0002 | N52: =SUMIFS($H$5:H52,$F$5:F52,F52)-SUMIFS($I$5:I52,$F$5:F52,F52) -> -11500
A53: 15 | B53: 46368.792 | C53: Vente | D53: Vente | E53: Achat BAR — Jean | F53: L-WAL-W04-P | G53: =IFERROR(INDEX('Plan de comptes'!$B$5:$B$41,MATCH(F53,'Plan de comptes'!$A$5:$A$41,0)),"COMPTE INCONNU") -> Portefeuille W04 Jean — crédits payés | H53: 6000 | J53: =IFERROR(INDEX('Plan de comptes'!$D$5:$D$41,MATCH(F53,'Plan de comptes'!$A$5:$A$41,0)),"?") -> W04 | K53: =SUMIFS($H$5:$H$500,$A$5:$A$500,A53)-SUMIFS($I$5:$I$500,$A$5:$A$500,A53) -> 0 | L53: ONLINE | M53: TPE-BAR-01:0003 | N53: =SUMIFS($H$5:H53,$F$5:F53,F53)-SUMIFS($I$5:I53,$F$5:F53,F53) -> -3000
A54: 15 | B54: 46368.792 | C54: Vente | D54: Vente | E54: Vente BAR — Jean | F54: L-MCH-BAR | G54: =IFERROR(INDEX('Plan de comptes'!$B$5:$B$41,MATCH(F54,'Plan de comptes'!$A$5:$A$41,0)),"COMPTE INCONNU") -> Commerçant interne — Bar de l'organisateur | I54: =H53 -> 6000 | J54: =IFERROR(INDEX('Plan de comptes'!$D$5:$D$41,MATCH(F54,'Plan de comptes'!$A$5:$A$41,0)),"?") -> BAR | K54: =SUMIFS($H$5:$H$500,$A$5:$A$500,A54)-SUMIFS($I$5:$I$500,$A$5:$A$500,A54) -> 0 | L54: ONLINE | M54: TPE-BAR-01:0003 | N54: =SUMIFS($H$5:H54,$F$5:F54,F54)-SUMIFS($I$5:I54,$F$5:F54,F54) -> -17500
A55: 16 | B55: 46368.794 | C55: Annulation vente | D55: Annulation | E55: Contre-passation de T15 (erreur de saisie) | F55: L-MCH-BAR | G55: =IFERROR(INDEX('Plan de comptes'!$B$5:$B$41,MATCH(F55,'Plan de comptes'!$A$5:$A$41,0)),"COMPTE INCONNU") -> Commerçant interne — Bar de l'organisateur | H55: =I54 -> 6000 | J55: =IFERROR(INDEX('Plan de comptes'!$D$5:$D$41,MATCH(F55,'Plan de comptes'!$A$5:$A$41,0)),"?") -> BAR | K55: =SUMIFS($H$5:$H$500,$A$5:$A$500,A55)-SUMIFS($I$5:$I$500,$A$5:$A$500,A55) -> 0 | L55: ONLINE | M55: TPE-BAR-01:0004 | N55: =SUMIFS($H$5:H55,$F$5:F55,F55)-SUMIFS($I$5:I55,$F$5:F55,F55) -> -11500
A56: 16 | B56: 46368.794 | C56: Annulation vente | D56: Annulation | E56: Contre-passation de T15 (erreur de saisie) | F56: L-WAL-W04-P | G56: =IFERROR(INDEX('Plan de comptes'!$B$5:$B$41,MATCH(F56,'Plan de comptes'!$A$5:$A$41,0)),"COMPTE INCONNU") -> Portefeuille W04 Jean — crédits payés | I56: =H53 -> 6000 | J56: =IFERROR(INDEX('Plan de comptes'!$D$5:$D$41,MATCH(F56,'Plan de comptes'!$A$5:$A$41,0)),"?") -> W04 | K56: =SUMIFS($H$5:$H$500,$A$5:$A$500,A56)-SUMIFS($I$5:$I$500,$A$5:$A$500,A56) -> 0 | L56: ONLINE | M56: TPE-BAR-01:0004 | N56: =SUMIFS($H$5:H56,$F$5:F56,F56)-SUMIFS($I$5:I56,$F$5:F56,F56) -> -9000
A57: 17 | B57: 46368.794 | C57: Vente | D57: Vente | E57: Achat BAR — Jean (montant corrigé) | F57: L-WAL-W04-P | G57: =IFERROR(INDEX('Plan de comptes'!$B$5:$B$41,MATCH(F57,'Plan de comptes'!$A$5:$A$41,0)),"COMPTE INCONNU") -> Portefeuille W04 Jean — crédits payés | H57: 3000 | J57: =IFERROR(INDEX('Plan de comptes'!$D$5:$D$41,MATCH(F57,'Plan de comptes'!$A$5:$A$41,0)),"?") -> W04 | K57: =SUMIFS($H$5:$H$500,$A$5:$A$500,A57)-SUMIFS($I$5:$I$500,$A$5:$A$500,A57) -> 0 | L57: ONLINE | M57: TPE-BAR-01:0005 | N57: =SUMIFS($H$5:H57,$F$5:F57,F57)-SUMIFS($I$5:I57,$F$5:F57,F57) -> -6000
A58: 17 | B58: 46368.794 | C58: Vente | D58: Vente | E58: Vente BAR — Jean (montant corrigé) | F58: L-MCH-BAR | G58: =IFERROR(INDEX('Plan de comptes'!$B$5:$B$41,MATCH(F58,'Plan de comptes'!$A$5:$A$41,0)),"COMPTE INCONNU") -> Commerçant interne — Bar de l'organisateur | I58: =H57 -> 3000 | J58: =IFERROR(INDEX('Plan de comptes'!$D$5:$D$41,MATCH(F58,'Plan de comptes'!$A$5:$A$41,0)),"?") -> BAR | K58: =SUMIFS($H$5:$H$500,$A$5:$A$500,A58)-SUMIFS($I$5:$I$500,$A$5:$A$500,A58) -> 0 | L58: ONLINE | M58: TPE-BAR-01:0005 | N58: =SUMIFS($H$5:H58,$F$5:F58,F58)-SUMIFS($I$5:I58,$F$5:F58,F58) -> -14500
A59: 18 | B59: 46368.847 | C59: Vente | D59: Vente | E59: Achat TEE — Aminata | F59: L-WAL-W05-P | G59: =IFERROR(INDEX('Plan de comptes'!$B$5:$B$41,MATCH(F59,'Plan de comptes'!$A$5:$A$41,0)),"COMPTE INCONNU") -> Portefeuille W05 Aminata — crédits payés | H59: 8000 | J59: =IFERROR(INDEX('Plan de comptes'!$D$5:$D$41,MATCH(F59,'Plan de comptes'!$A$5:$A$41,0)),"?") -> W05 | K59: =SUMIFS($H$5:$H$500,$A$5:$A$500,A59)-SUMIFS($I$5:$I$500,$A$5:$A$500,A59) -> 0 | L59: ONLINE | M59: TPE-TEE-01:0002 | N59: =SUMIFS($H$5:H59,$F$5:F59,F59)-SUMIFS($I$5:I59,$F$5:F59,F59) -> -14000
A60: 18 | B60: 46368.847 | C60: Vente | D60: Vente | E60: Vente TEE — Aminata | F60: L-MCH-TEE | G60: =IFERROR(INDEX('Plan de comptes'!$B$5:$B$41,MATCH(F60,'Plan de comptes'!$A$5:$A$41,0)),"COMPTE INCONNU") -> Commerçant externe — Tee-shirts | I60: =H59 -> 8000 | J60: =IFERROR(INDEX('Plan de comptes'!$D$5:$D$41,MATCH(F60,'Plan de comptes'!$A$5:$A$41,0)),"?") -> TEE | K60: =SUMIFS($H$5:$H$500,$A$5:$A$500,A60)-SUMIFS($I$5:$I$500,$A$5:$A$500,A60) -> 0 | L60: ONLINE | M60: TPE-TEE-01:0002 | N60: =SUMIFS($H$5:H60,$F$5:F60,F60)-SUMIFS($I$5:I60,$F$5:F60,F60) -> -18800
A61: 18 | B61: 46368.847 | C61: Vente | D61: Commission | E61: Commission TTC sur vente TEE | F61: L-MCH-TEE | G61: =IFERROR(INDEX('Plan de comptes'!$B$5:$B$41,MATCH(F61,'Plan de comptes'!$A$5:$A$41,0)),"COMPTE INCONNU") -> Commerçant externe — Tee-shirts | H61: =ROUND(I60*Paramètres!$C$13,0) -> 800 | J61: =IFERROR(INDEX('Plan de comptes'!$D$5:$D$41,MATCH(F61,'Plan de comptes'!$A$5:$A$41,0)),"?") -> TEE | K61: =SUMIFS($H$5:$H$500,$A$5:$A$500,A61)-SUMIFS($I$5:$I$500,$A$5:$A$500,A61) -> 0 | L61: ONLINE | M61: TPE-TEE-01:0002 | N61: =SUMIFS($H$5:H61,$F$5:F61,F61)-SUMIFS($I$5:I61,$F$5:F61,F61) -> -18000
A62: 18 | B62: 46368.847 | C62: Vente | D62: Commission | E62: Commission sur vente TEE (HT) | F62: L-ORG-COM | G62: =IFERROR(INDEX('Plan de comptes'!$B$5:$B$41,MATCH(F62,'Plan de comptes'!$A$5:$A$41,0)),"COMPTE INCONNU") -> Organisateur — commissions | I62: =H61-ROUND(H61*Paramètres!$C$21/(1+Paramètres!$C$21),0) -> 678 | J62: =IFERROR(INDEX('Plan de comptes'!$D$5:$D$41,MATCH(F62,'Plan de comptes'!$A$5:$A$41,0)),"?") -> ORG | K62: =SUMIFS($H$5:$H$500,$A$5:$A$500,A62)-SUMIFS($I$5:$I$500,$A$5:$A$500,A62) -> 0 | L62: ONLINE | M62: TPE-TEE-01:0002 | N62: =SUMIFS($H$5:H62,$F$5:F62,F62)-SUMIFS($I$5:I62,$F$5:F62,F62) -> -3220
A63: 18 | B63: 46368.847 | C63: Vente | D63: Commission | E63: Commission sur vente TEE (taxe collectée) | F63: L-ORG-TVA | G63: =IFERROR(INDEX('Plan de comptes'!$B$5:$B$41,MATCH(F63,'Plan de comptes'!$A$5:$A$41,0)),"COMPTE INCONNU") -> Organisateur — taxe collectée (à reverser à l'État) | I63: =ROUND(H61*Paramètres!$C$21/(1+Paramètres!$C$21),0) -> 122 | J63: =IFERROR(INDEX('Plan de comptes'!$D$5:$D$41,MATCH(F63,'Plan de comptes'!$A$5:$A$41,0)),"?") -> ORG | K63: =SUMIFS($H$5:$H$500,$A$5:$A$500,A63)-SUMIFS($I$5:$I$500,$A$5:$A$500,A63) -> 0 | L63: ONLINE | M63: TPE-TEE-01:0002 | N63: =SUMIFS($H$5:H63,$F$5:F63,F63)-SUMIFS($I$5:I63,$F$5:F63,F63) -> -1343
A64: 19 | B64: 46368.906 | C64: Vente | D64: Vente | E64: Achat FOOD — Aminata | F64: L-WAL-W05-P | G64: =IFERROR(INDEX('Plan de comptes'!$B$5:$B$41,MATCH(F64,'Plan de comptes'!$A$5:$A$41,0)),"COMPTE INCONNU") -> Portefeuille W05 Aminata — crédits payés | H64: 5000 | J64: =IFERROR(INDEX('Plan de comptes'!$D$5:$D$41,MATCH(F64,'Plan de comptes'!$A$5:$A$41,0)),"?") -> W05 | K64: =SUMIFS($H$5:$H$500,$A$5:$A$500,A64)-SUMIFS($I$5:$I$500,$A$5:$A$500,A64) -> 0 | L64: ONLINE | M64: TPE-FOOD-01:0003 | N64: =SUMIFS($H$5:H64,$F$5:F64,F64)-SUMIFS($I$5:I64,$F$5:F64,F64) -> -9000
A65: 19 | B65: 46368.906 | C65: Vente | D65: Vente | E65: Vente FOOD — Aminata | F65: L-MCH-FOOD | G65: =IFERROR(INDEX('Plan de comptes'!$B$5:$B$41,MATCH(F65,'Plan de comptes'!$A$5:$A$41,0)),"COMPTE INCONNU") -> Commerçant externe — Food truck | I65: =H64 -> 5000 | J65: =IFERROR(INDEX('Plan de comptes'!$D$5:$D$41,MATCH(F65,'Plan de comptes'!$A$5:$A$41,0)),"?") -> FOOD | K65: =SUMIFS($H$5:$H$500,$A$5:$A$500,A65)-SUMIFS($I$5:$I$500,$A$5:$A$500,A65) -> 0 | L65: ONLINE | M65: TPE-FOOD-01:0003 | N65: =SUMIFS($H$5:H65,$F$5:F65,F65)-SUMIFS($I$5:I65,$F$5:F65,F65) -> -18200
A66: 19 | B66: 46368.906 | C66: Vente | D66: Commission | E66: Commission TTC sur vente FOOD | F66: L-MCH-FOOD | G66: =IFERROR(INDEX('Plan de comptes'!$B$5:$B$41,MATCH(F66,'Plan de comptes'!$A$5:$A$41,0)),"COMPTE INCONNU") -> Commerçant externe — Food truck | H66: =ROUND(I65*Paramètres!$C$12,0) -> 600 | J66: =IFERROR(INDEX('Plan de comptes'!$D$5:$D$41,MATCH(F66,'Plan de comptes'!$A$5:$A$41,0)),"?") -> FOOD | K66: =SUMIFS($H$5:$H$500,$A$5:$A$500,A66)-SUMIFS($I$5:$I$500,$A$5:$A$500,A66) -> 0 | L66: ONLINE | M66: TPE-FOOD-01:0003 | N66: =SUMIFS($H$5:H66,$F$5:F66,F66)-SUMIFS($I$5:I66,$F$5:F66,F66) -> -17600
A67: 19 | B67: 46368.906 | C67: Vente | D67: Commission | E67: Commission sur vente FOOD (HT) | F67: L-ORG-COM | G67: =IFERROR(INDEX('Plan de comptes'!$B$5:$B$41,MATCH(F67,'Plan de comptes'!$A$5:$A$41,0)),"COMPTE INCONNU") -> Organisateur — commissions | I67: =H66-ROUND(H66*Paramètres!$C$21/(1+Paramètres!$C$21),0) -> 508 | J67: =IFERROR(INDEX('Plan de comptes'!$D$5:$D$41,MATCH(F67,'Plan de comptes'!$A$5:$A$41,0)),"?") -> ORG | K67: =SUMIFS($H$5:$H$500,$A$5:$A$500,A67)-SUMIFS($I$5:$I$500,$A$5:$A$500,A67) -> 0 | L67: ONLINE | M67: TPE-FOOD-01:0003 | N67: =SUMIFS($H$5:H67,$F$5:F67,F67)-SUMIFS($I$5:I67,$F$5:F67,F67) -> -3728
A68: 19 | B68: 46368.906 | C68: Vente | D68: Commission | E68: Commission sur vente FOOD (taxe collectée) | F68: L-ORG-TVA | G68: =IFERROR(INDEX('Plan de comptes'!$B$5:$B$41,MATCH(F68,'Plan de comptes'!$A$5:$A$41,0)),"COMPTE INCONNU") -> Organisateur — taxe collectée (à reverser à l'État) | I68: =ROUND(H66*Paramètres!$C$21/(1+Paramètres!$C$21),0) -> 92 | J68: =IFERROR(INDEX('Plan de comptes'!$D$5:$D$41,MATCH(F68,'Plan de comptes'!$A$5:$A$41,0)),"?") -> ORG | K68: =SUMIFS($H$5:$H$500,$A$5:$A$500,A68)-SUMIFS($I$5:$I$500,$A$5:$A$500,A68) -> 0 | L68: ONLINE | M68: TPE-FOOD-01:0003 | N68: =SUMIFS($H$5:H68,$F$5:F68,F68)-SUMIFS($I$5:I68,$F$5:F68,F68) -> -1435
A69: 20 | B69: 46368.917 | C69: Vente | D69: Vente | E69: Achat BAR — Ibou (crédits offerts) | F69: L-WAL-W06-X | G69: =IFERROR(INDEX('Plan de comptes'!$B$5:$B$41,MATCH(F69,'Plan de comptes'!$A$5:$A$41,0)),"COMPTE INCONNU") -> Portefeuille W06 Ibou — crédits offerts | H69: 4000 | J69: =IFERROR(INDEX('Plan de comptes'!$D$5:$D$41,MATCH(F69,'Plan de comptes'!$A$5:$A$41,0)),"?") -> W06 | K69: =SUMIFS($H$5:$H$500,$A$5:$A$500,A69)-SUMIFS($I$5:$I$500,$A$5:$A$500,A69) -> 0 | L69: ONLINE | M69: TPE-BAR-01:0006 | N69: =SUMIFS($H$5:H69,$F$5:F69,F69)-SUMIFS($I$5:I69,$F$5:F69,F69) -> -2000
A70: 20 | B70: 46368.917 | C70: Vente | D70: Vente | E70: Vente BAR — Ibou (crédits offerts) | F70: L-MCH-BAR | G70: =IFERROR(INDEX('Plan de comptes'!$B$5:$B$41,MATCH(F70,'Plan de comptes'!$A$5:$A$41,0)),"COMPTE INCONNU") -> Commerçant interne — Bar de l'organisateur | I70: =H69 -> 4000 | J70: =IFERROR(INDEX('Plan de comptes'!$D$5:$D$41,MATCH(F70,'Plan de comptes'!$A$5:$A$41,0)),"?") -> BAR | K70: =SUMIFS($H$5:$H$500,$A$5:$A$500,A70)-SUMIFS($I$5:$I$500,$A$5:$A$500,A70) -> 0 | L70: ONLINE | M70: TPE-BAR-01:0006 | N70: =SUMIFS($H$5:H70,$F$5:F70,F70)-SUMIFS($I$5:I70,$F$5:F70,F70) -> -18500
A71: 21 | B71: 46369.542 | C71: Vente | D71: Vente | E71: Achat FOOD — Ibou (crédits offerts) | F71: L-WAL-W06-X | G71: =IFERROR(INDEX('Plan de comptes'!$B$5:$B$41,MATCH(F71,'Plan de comptes'!$A$5:$A$41,0)),"COMPTE INCONNU") -> Portefeuille W06 Ibou — crédits offerts | H71: 1000 | J71: =IFERROR(INDEX('Plan de comptes'!$D$5:$D$41,MATCH(F71,'Plan de comptes'!$A$5:$A$41,0)),"?") -> W06 | K71: =SUMIFS($H$5:$H$500,$A$5:$A$500,A71)-SUMIFS($I$5:$I$500,$A$5:$A$500,A71) -> 0 | L71: ONLINE | M71: TPE-FOOD-01:0004 | N71: =SUMIFS($H$5:H71,$F$5:F71,F71)-SUMIFS($I$5:I71,$F$5:F71,F71) -> -1000
A72: 21 | B72: 46369.542 | C72: Vente | D72: Vente | E72: Vente FOOD — Ibou (crédits offerts) | F72: L-MCH-FOOD | G72: =IFERROR(INDEX('Plan de comptes'!$B$5:$B$41,MATCH(F72,'Plan de comptes'!$A$5:$A$41,0)),"COMPTE INCONNU") -> Commerçant externe — Food truck | I72: =H71 -> 1000 | J72: =IFERROR(INDEX('Plan de comptes'!$D$5:$D$41,MATCH(F72,'Plan de comptes'!$A$5:$A$41,0)),"?") -> FOOD | K72: =SUMIFS($H$5:$H$500,$A$5:$A$500,A72)-SUMIFS($I$5:$I$500,$A$5:$A$500,A72) -> 0 | L72: ONLINE | M72: TPE-FOOD-01:0004 | N72: =SUMIFS($H$5:H72,$F$5:F72,F72)-SUMIFS($I$5:I72,$F$5:F72,F72) -> -18600
A73: 21 | B73: 46369.542 | C73: Vente | D73: Commission | E73: Commission TTC sur vente FOOD | F73: L-MCH-FOOD | G73: =IFERROR(INDEX('Plan de comptes'!$B$5:$B$41,MATCH(F73,'Plan de comptes'!$A$5:$A$41,0)),"COMPTE INCONNU") -> Commerçant externe — Food truck | H73: =ROUND(I72*Paramètres!$C$12,0) -> 120 | J73: =IFERROR(INDEX('Plan de comptes'!$D$5:$D$41,MATCH(F73,'Plan de comptes'!$A$5:$A$41,0)),"?") -> FOOD | K73: =SUMIFS($H$5:$H$500,$A$5:$A$500,A73)-SUMIFS($I$5:$I$500,$A$5:$A$500,A73) -> 0 | L73: ONLINE | M73: TPE-FOOD-01:0004 | N73: =SUMIFS($H$5:H73,$F$5:F73,F73)-SUMIFS($I$5:I73,$F$5:F73,F73) -> -18480
A74: 21 | B74: 46369.542 | C74: Vente | D74: Commission | E74: Commission sur vente FOOD (HT) | F74: L-ORG-COM | G74: =IFERROR(INDEX('Plan de comptes'!$B$5:$B$41,MATCH(F74,'Plan de comptes'!$A$5:$A$41,0)),"COMPTE INCONNU") -> Organisateur — commissions | I74: =H73-ROUND(H73*Paramètres!$C$21/(1+Paramètres!$C$21),0) -> 102 | J74: =IFERROR(INDEX('Plan de comptes'!$D$5:$D$41,MATCH(F74,'Plan de comptes'!$A$5:$A$41,0)),"?") -> ORG | K74: =SUMIFS($H$5:$H$500,$A$5:$A$500,A74)-SUMIFS($I$5:$I$500,$A$5:$A$500,A74) -> 0 | L74: ONLINE | M74: TPE-FOOD-01:0004 | N74: =SUMIFS($H$5:H74,$F$5:F74,F74)-SUMIFS($I$5:I74,$F$5:F74,F74) -> -3830
A75: 21 | B75: 46369.542 | C75: Vente | D75: Commission | E75: Commission sur vente FOOD (taxe collectée) | F75: L-ORG-TVA | G75: =IFERROR(INDEX('Plan de comptes'!$B$5:$B$41,MATCH(F75,'Plan de comptes'!$A$5:$A$41,0)),"COMPTE INCONNU") -> Organisateur — taxe collectée (à reverser à l'État) | I75: =ROUND(H73*Paramètres!$C$21/(1+Paramètres!$C$21),0) -> 18 | J75: =IFERROR(INDEX('Plan de comptes'!$D$5:$D$41,MATCH(F75,'Plan de comptes'!$A$5:$A$41,0)),"?") -> ORG | K75: =SUMIFS($H$5:$H$500,$A$5:$A$500,A75)-SUMIFS($I$5:$I$500,$A$5:$A$500,A75) -> 0 | L75: ONLINE | M75: TPE-FOOD-01:0004 | N75: =SUMIFS($H$5:H75,$F$5:F75,F75)-SUMIFS($I$5:I75,$F$5:F75,F75) -> -1453
A76: 22 | B76: 46369.896 | C76: Vente hors ligne | D76: Vente | E76: Achat FOOD hors ligne — Jean (synchro : solde insuffisant) | F76: L-WAL-W04-P | G76: =IFERROR(INDEX('Plan de comptes'!$B$5:$B$41,MATCH(F76,'Plan de comptes'!$A$5:$A$41,0)),"COMPTE INCONNU") -> Portefeuille W04 Jean — crédits payés | H76: =MIN(I78,-(SUMIFS($H$5:$H$75,$F$5:$F$75,"L-WAL-W04-P")-SUMIFS($I$5:$I$75,$F$5:$F$75,"L-WAL-W04-P"))) -> 6000 | J76: =IFERROR(INDEX('Plan de comptes'!$D$5:$D$41,MATCH(F76,'Plan de comptes'!$A$5:$A$41,0)),"?") -> W04 | K76: =SUMIFS($H$5:$H$500,$A$5:$A$500,A76)-SUMIFS($I$5:$I$500,$A$5:$A$500,A76) -> 0 | L76: OFFLINE_SYNC | M76: TPE-FOOD-02:0087 | N76: =SUMIFS($H$5:H76,$F$5:F76,F76)-SUMIFS($I$5:I76,$F$5:F76,F76) -> 0
A77: 22 | B77: 46369.896 | C77: Vente hors ligne | D77: Vente | E77: Part non couverte → compte d'attente (anomalie) | F77: S-ATTENTE | G77: =IFERROR(INDEX('Plan de comptes'!$B$5:$B$41,MATCH(F77,'Plan de comptes'!$A$5:$A$41,0)),"COMPTE INCONNU") -> Compte d'attente — anomalies | H77: =I78-H76 -> 3000 | J77: =IFERROR(INDEX('Plan de comptes'!$D$5:$D$41,MATCH(F77,'Plan de comptes'!$A$5:$A$41,0)),"?") -> — | K77: =SUMIFS($H$5:$H$500,$A$5:$A$500,A77)-SUMIFS($I$5:$I$500,$A$5:$A$500,A77) -> 0 | L77: OFFLINE_SYNC | M77: TPE-FOOD-02:0087 | N77: =SUMIFS($H$5:H77,$F$5:F77,F77)-SUMIFS($I$5:I77,$F$5:F77,F77) -> 3000
A78: 22 | B78: 46369.896 | C78: Vente hors ligne | D78: Vente | E78: Vente FOOD hors ligne — Jean (commerçant garanti) | F78: L-MCH-FOOD | G78: =IFERROR(INDEX('Plan de comptes'!$B$5:$B$41,MATCH(F78,'Plan de comptes'!$A$5:$A$41,0)),"COMPTE INCONNU") -> Commerçant externe — Food truck | I78: 9000 | J78: =IFERROR(INDEX('Plan de comptes'!$D$5:$D$41,MATCH(F78,'Plan de comptes'!$A$5:$A$41,0)),"?") -> FOOD | K78: =SUMIFS($H$5:$H$500,$A$5:$A$500,A78)-SUMIFS($I$5:$I$500,$A$5:$A$500,A78) -> 0 | L78: OFFLINE_SYNC | M78: TPE-FOOD-02:0087 | N78: =SUMIFS($H$5:H78,$F$5:F78,F78)-SUMIFS($I$5:I78,$F$5:F78,F78) -> -27480
A79: 22 | B79: 46369.896 | C79: Vente hors ligne | D79: Commission | E79: Commission TTC sur vente FOOD | F79: L-MCH-FOOD | G79: =IFERROR(INDEX('Plan de comptes'!$B$5:$B$41,MATCH(F79,'Plan de comptes'!$A$5:$A$41,0)),"COMPTE INCONNU") -> Commerçant externe — Food truck | H79: =ROUND(I78*Paramètres!$C$12,0) -> 1080 | J79: =IFERROR(INDEX('Plan de comptes'!$D$5:$D$41,MATCH(F79,'Plan de comptes'!$A$5:$A$41,0)),"?") -> FOOD | K79: =SUMIFS($H$5:$H$500,$A$5:$A$500,A79)-SUMIFS($I$5:$I$500,$A$5:$A$500,A79) -> 0 | L79: OFFLINE_SYNC | M79: TPE-FOOD-02:0087 | N79: =SUMIFS($H$5:H79,$F$5:F79,F79)-SUMIFS($I$5:I79,$F$5:F79,F79) -> -26400
A80: 22 | B80: 46369.896 | C80: Vente hors ligne | D80: Commission | E80: Commission sur vente FOOD (HT) | F80: L-ORG-COM | G80: =IFERROR(INDEX('Plan de comptes'!$B$5:$B$41,MATCH(F80,'Plan de comptes'!$A$5:$A$41,0)),"COMPTE INCONNU") -> Organisateur — commissions | I80: =H79-ROUND(H79*Paramètres!$C$21/(1+Paramètres!$C$21),0) -> 915 | J80: =IFERROR(INDEX('Plan de comptes'!$D$5:$D$41,MATCH(F80,'Plan de comptes'!$A$5:$A$41,0)),"?") -> ORG | K80: =SUMIFS($H$5:$H$500,$A$5:$A$500,A80)-SUMIFS($I$5:$I$500,$A$5:$A$500,A80) -> 0 | L80: OFFLINE_SYNC | M80: TPE-FOOD-02:0087 | N80: =SUMIFS($H$5:H80,$F$5:F80,F80)-SUMIFS($I$5:I80,$F$5:F80,F80) -> -4745
A81: 22 | B81: 46369.896 | C81: Vente hors ligne | D81: Commission | E81: Commission sur vente FOOD (taxe collectée) | F81: L-ORG-TVA | G81: =IFERROR(INDEX('Plan de comptes'!$B$5:$B$41,MATCH(F81,'Plan de comptes'!$A$5:$A$41,0)),"COMPTE INCONNU") -> Organisateur — taxe collectée (à reverser à l'État) | I81: =ROUND(H79*Paramètres!$C$21/(1+Paramètres!$C$21),0) -> 165 | J81: =IFERROR(INDEX('Plan de comptes'!$D$5:$D$41,MATCH(F81,'Plan de comptes'!$A$5:$A$41,0)),"?") -> ORG | K81: =SUMIFS($H$5:$H$500,$A$5:$A$500,A81)-SUMIFS($I$5:$I$500,$A$5:$A$500,A81) -> 0 | L81: OFFLINE_SYNC | M81: TPE-FOOD-02:0087 | N81: =SUMIFS($H$5:H81,$F$5:F81,F81)-SUMIFS($I$5:I81,$F$5:F81,F81) -> -1618
A82: 23 | B82: 46369.979 | C82: Caution rendue | D82: Caution | E82: Bracelet rendu : caution recréditée sur le solde (mode C) — Aminata | F82: L-ORG-CAUTION | G82: =IFERROR(INDEX('Plan de comptes'!$B$5:$B$41,MATCH(F82,'Plan de comptes'!$A$5:$A$41,0)),"COMPTE INCONNU") -> Organisateur — cautions détenues (à rendre) | H82: =Paramètres!$C$23 -> 2000 | J82: =IFERROR(INDEX('Plan de comptes'!$D$5:$D$41,MATCH(F82,'Plan de comptes'!$A$5:$A$41,0)),"?") -> ORG | K82: =SUMIFS($H$5:$H$500,$A$5:$A$500,A82)-SUMIFS($I$5:$I$500,$A$5:$A$500,A82) -> 0 | L82: ONLINE | M82: deposit-refund:W05:1 | N82: =SUMIFS($H$5:H82,$F$5:F82,F82)-SUMIFS($I$5:I82,$F$5:F82,F82) -> -2000
A83: 23 | B83: 46369.979 | C83: Caution rendue | D83: Caution | E83: Caution recréditée — Aminata | F83: L-WAL-W05-P | G83: =IFERROR(INDEX('Plan de comptes'!$B$5:$B$41,MATCH(F83,'Plan de comptes'!$A$5:$A$41,0)),"COMPTE INCONNU") -> Portefeuille W05 Aminata — crédits payés | I83: =H82 -> 2000 | J83: =IFERROR(INDEX('Plan de comptes'!$D$5:$D$41,MATCH(F83,'Plan de comptes'!$A$5:$A$41,0)),"?") -> W05 | K83: =SUMIFS($H$5:$H$500,$A$5:$A$500,A83)-SUMIFS($I$5:$I$500,$A$5:$A$500,A83) -> 0 | L83: ONLINE | M83: deposit-refund:W05:1 | N83: =SUMIFS($H$5:H83,$F$5:F83,F83)-SUMIFS($I$5:I83,$F$5:F83,F83) -> -11000
A84: 24 | B84: 46370.042 | C84: Fermeture caisse | D84: Caisse | E84: Espèces comptées, mises en transit | F84: A-TRANSIT | G84: =IFERROR(INDEX('Plan de comptes'!$B$5:$B$41,MATCH(F84,'Plan de comptes'!$A$5:$A$41,0)),"COMPTE INCONNU") -> Espèces en transit vers la banque | H84: =Paramètres!$C$24 -> 36800 | J84: =IFERROR(INDEX('Plan de comptes'!$D$5:$D$41,MATCH(F84,'Plan de comptes'!$A$5:$A$41,0)),"?") -> ORG | K84: =SUMIFS($H$5:$H$500,$A$5:$A$500,A84)-SUMIFS($I$5:$I$500,$A$5:$A$500,A84) -> 0 | L84: BACKOFFICE | M84: cash-session:C1:2026-12-13 | N84: =SUMIFS($H$5:H84,$F$5:F84,F84)-SUMIFS($I$5:I84,$F$5:F84,F84) -> 36800
A85: 24 | B85: 46370.042 | C85: Fermeture caisse | D85: Caisse | E85: Écart de caisse (manque / surplus) | F85: L-ORG-PERTES | G85: =IFERROR(INDEX('Plan de comptes'!$B$5:$B$41,MATCH(F85,'Plan de comptes'!$A$5:$A$41,0)),"COMPTE INCONNU") -> Organisateur — pertes (fraude, écarts de caisse) | H85: =MAX(0,(SUMIFS($H$5:$H$83,$F$5:$F$83,"A-CAISSE-C1")-SUMIFS($I$5:$I$83,$F$5:$F$83,"A-CAISSE-C1"))-H84) -> 200 | I85: =MAX(0,H84-(SUMIFS($H$5:$H$83,$F$5:$F$83,"A-CAISSE-C1")-SUMIFS($I$5:$I$83,$F$5:$F$83,"A-CAISSE-C1"))) -> 0 | J85: =IFERROR(INDEX('Plan de comptes'!$D$5:$D$41,MATCH(F85,'Plan de comptes'!$A$5:$A$41,0)),"?") -> ORG | K85: =SUMIFS($H$5:$H$500,$A$5:$A$500,A85)-SUMIFS($I$5:$I$500,$A$5:$A$500,A85) -> 0 | L85: BACKOFFICE | M85: cash-session:C1:2026-12-13 | N85: =SUMIFS($H$5:H85,$F$5:F85,F85)-SUMIFS($I$5:I85,$F$5:F85,F85) -> 200
A86: 24 | B86: 46370.042 | C86: Fermeture caisse | D86: Caisse | E86: Solde théorique de la caisse C1 | F86: A-CAISSE-C1 | G86: =IFERROR(INDEX('Plan de comptes'!$B$5:$B$41,MATCH(F86,'Plan de comptes'!$A$5:$A$41,0)),"COMPTE INCONNU") -> Caisse de recharge C1 (espèces) | I86: =(SUMIFS($H$5:$H$83,$F$5:$F$83,"A-CAISSE-C1")-SUMIFS($I$5:$I$83,$F$5:$F$83,"A-CAISSE-C1")) -> 37000 | J86: =IFERROR(INDEX('Plan de comptes'!$D$5:$D$41,MATCH(F86,'Plan de comptes'!$A$5:$A$41,0)),"?") -> ORG | K86: =SUMIFS($H$5:$H$500,$A$5:$A$500,A86)-SUMIFS($I$5:$I$500,$A$5:$A$500,A86) -> 0 | L86: BACKOFFICE | M86: cash-session:C1:2026-12-13 | N86: =SUMIFS($H$5:H86,$F$5:F86,F86)-SUMIFS($I$5:I86,$F$5:F86,F86) -> 0
A87: 25 | B87: 46370.417 | C87: Résolution anomalie | D87: Perte | E87: Perte hors ligne supportée par l'organisateur (offline_loss_bearer) | F87: L-ORG-PERTES | G87: =IFERROR(INDEX('Plan de comptes'!$B$5:$B$41,MATCH(F87,'Plan de comptes'!$A$5:$A$41,0)),"COMPTE INCONNU") -> Organisateur — pertes (fraude, écarts de caisse) | H87: =(SUMIFS($H$5:$H$86,$F$5:$F$86,"S-ATTENTE")-SUMIFS($I$5:$I$86,$F$5:$F$86,"S-ATTENTE")) -> 3000 | J87: =IFERROR(INDEX('Plan de comptes'!$D$5:$D$41,MATCH(F87,'Plan de comptes'!$A$5:$A$41,0)),"?") -> ORG | K87: =SUMIFS($H$5:$H$500,$A$5:$A$500,A87)-SUMIFS($I$5:$I$500,$A$5:$A$500,A87) -> 0 | L87: BACKOFFICE | M87: anomaly:AN-0001 | N87: =SUMIFS($H$5:H87,$F$5:F87,F87)-SUMIFS($I$5:I87,$F$5:F87,F87) -> 3200
A88: 25 | B88: 46370.417 | C88: Résolution anomalie | D88: Perte | E88: Solde du compte d'attente | F88: S-ATTENTE | G88: =IFERROR(INDEX('Plan de comptes'!$B$5:$B$41,MATCH(F88,'Plan de comptes'!$A$5:$A$41,0)),"COMPTE INCONNU") -> Compte d'attente — anomalies | I88: =H87 -> 3000 | J88: =IFERROR(INDEX('Plan de comptes'!$D$5:$D$41,MATCH(F88,'Plan de comptes'!$A$5:$A$41,0)),"?") -> — | K88: =SUMIFS($H$5:$H$500,$A$5:$A$500,A88)-SUMIFS($I$5:$I$500,$A$5:$A$500,A88) -> 0 | L88: BACKOFFICE | M88: anomaly:AN-0001 | N88: =SUMIFS($H$5:H88,$F$5:F88,F88)-SUMIFS($I$5:I88,$F$5:F88,F88) -> 0
A89: 26 | B89: 46371.375 | C89: Dépôt espèces | D89: Banque | E89: Dépôt des espèces en banque | F89: A-BANQUE | G89: =IFERROR(INDEX('Plan de comptes'!$B$5:$B$41,MATCH(F89,'Plan de comptes'!$A$5:$A$41,0)),"COMPTE INCONNU") -> Banque — compte cantonné du pool | H89: =(SUMIFS($H$5:$H$88,$F$5:$F$88,"A-TRANSIT")-SUMIFS($I$5:$I$88,$F$5:$F$88,"A-TRANSIT")) -> 36800 | J89: =IFERROR(INDEX('Plan de comptes'!$D$5:$D$41,MATCH(F89,'Plan de comptes'!$A$5:$A$41,0)),"?") -> ORG | K89: =SUMIFS($H$5:$H$500,$A$5:$A$500,A89)-SUMIFS($I$5:$I$500,$A$5:$A$500,A89) -> 0 | L89: BATCH | M89: bank:DEP-771 | N89: =SUMIFS($H$5:H89,$F$5:F89,F89)-SUMIFS($I$5:I89,$F$5:F89,F89) -> 36800
A90: 26 | B90: 46371.375 | C90: Dépôt espèces | D90: Banque | E90: Dépôt des espèces en banque | F90: A-TRANSIT | G90: =IFERROR(INDEX('Plan de comptes'!$B$5:$B$41,MATCH(F90,'Plan de comptes'!$A$5:$A$41,0)),"COMPTE INCONNU") -> Espèces en transit vers la banque | I90: =H89 -> 36800 | J90: =IFERROR(INDEX('Plan de comptes'!$D$5:$D$41,MATCH(F90,'Plan de comptes'!$A$5:$A$41,0)),"?") -> ORG | K90: =SUMIFS($H$5:$H$500,$A$5:$A$500,A90)-SUMIFS($I$5:$I$500,$A$5:$A$500,A90) -> 0 | L90: BATCH | M90: bank:DEP-771 | N90: =SUMIFS($H$5:H90,$F$5:F90,F90)-SUMIFS($I$5:I90,$F$5:F90,F90) -> 0
A91: 27 | B91: 46371.5 | C91: Versement PSP | D91: Banque | E91: Versement net WAVE (rapproché avec le relevé) | F91: A-BANQUE | G91: =IFERROR(INDEX('Plan de comptes'!$B$5:$B$41,MATCH(F91,'Plan de comptes'!$A$5:$A$41,0)),"COMPTE INCONNU") -> Banque — compte cantonné du pool | H91: =(SUMIFS($H$5:$H$90,$F$5:$F$90,"A-PSP-WAVE")-SUMIFS($I$5:$I$90,$F$5:$F$90,"A-PSP-WAVE")) -> 19800 | J91: =IFERROR(INDEX('Plan de comptes'!$D$5:$D$41,MATCH(F91,'Plan de comptes'!$A$5:$A$41,0)),"?") -> ORG | K91: =SUMIFS($H$5:$H$500,$A$5:$A$500,A91)-SUMIFS($I$5:$I$500,$A$5:$A$500,A91) -> 0 | L91: BATCH | M91: stmt:wave:2026-12-15 | N91: =SUMIFS($H$5:H91,$F$5:F91,F91)-SUMIFS($I$5:I91,$F$5:F91,F91) -> 56600
A92: 27 | B92: 46371.5 | C92: Versement PSP | D92: Banque | E92: Versement net WAVE | F92: A-PSP-WAVE | G92: =IFERROR(INDEX('Plan de comptes'!$B$5:$B$41,MATCH(F92,'Plan de comptes'!$A$5:$A$41,0)),"COMPTE INCONNU") -> Créance sur Wave | I92: =H91 -> 19800 | J92: =IFERROR(INDEX('Plan de comptes'!$D$5:$D$41,MATCH(F92,'Plan de comptes'!$A$5:$A$41,0)),"?") -> ORG | K92: =SUMIFS($H$5:$H$500,$A$5:$A$500,A92)-SUMIFS($I$5:$I$500,$A$5:$A$500,A92) -> 0 | L92: BATCH | M92: stmt:wave:2026-12-15 | N92: =SUMIFS($H$5:H92,$F$5:F92,F92)-SUMIFS($I$5:I92,$F$5:F92,F92) -> 0
A93: 28 | B93: 46371.503 | C93: Versement PSP | D93: Banque | E93: Versement net OM (rapproché avec le relevé) | F93: A-BANQUE | G93: =IFERROR(INDEX('Plan de comptes'!$B$5:$B$41,MATCH(F93,'Plan de comptes'!$A$5:$A$41,0)),"COMPTE INCONNU") -> Banque — compte cantonné du pool | H93: =(SUMIFS($H$5:$H$92,$F$5:$F$92,"A-PSP-OM")-SUMIFS($I$5:$I$92,$F$5:$F$92,"A-PSP-OM")) -> 14775 | J93: =IFERROR(INDEX('Plan de comptes'!$D$5:$D$41,MATCH(F93,'Plan de comptes'!$A$5:$A$41,0)),"?") -> ORG | K93: =SUMIFS($H$5:$H$500,$A$5:$A$500,A93)-SUMIFS($I$5:$I$500,$A$5:$A$500,A93) -> 0 | L93: BATCH | M93: stmt:om:2026-12-15 | N93: =SUMIFS($H$5:H93,$F$5:F93,F93)-SUMIFS($I$5:I93,$F$5:F93,F93) -> 71375
A94: 28 | B94: 46371.503 | C94: Versement PSP | D94: Banque | E94: Versement net OM | F94: A-PSP-OM | G94: =IFERROR(INDEX('Plan de comptes'!$B$5:$B$41,MATCH(F94,'Plan de comptes'!$A$5:$A$41,0)),"COMPTE INCONNU") -> Créance sur Orange Money | I94: =H93 -> 14775 | J94: =IFERROR(INDEX('Plan de comptes'!$D$5:$D$41,MATCH(F94,'Plan de comptes'!$A$5:$A$41,0)),"?") -> ORG | K94: =SUMIFS($H$5:$H$500,$A$5:$A$500,A94)-SUMIFS($I$5:$I$500,$A$5:$A$500,A94) -> 0 | L94: BATCH | M94: stmt:om:2026-12-15 | N94: =SUMIFS($H$5:H94,$F$5:F94,F94)-SUMIFS($I$5:I94,$F$5:F94,F94) -> 0
A95: 29 | B95: 46372.375 | C95: Versement PSP | D95: Banque | E95: Versement net CARTE (rapproché avec le relevé) | F95: A-BANQUE | G95: =IFERROR(INDEX('Plan de comptes'!$B$5:$B$41,MATCH(F95,'Plan de comptes'!$A$5:$A$41,0)),"COMPTE INCONNU") -> Banque — compte cantonné du pool | H95: =(SUMIFS($H$5:$H$94,$F$5:$F$94,"A-PSP-CARTE")-SUMIFS($I$5:$I$94,$F$5:$F$94,"A-PSP-CARTE")) -> 29250 | J95: =IFERROR(INDEX('Plan de comptes'!$D$5:$D$41,MATCH(F95,'Plan de comptes'!$A$5:$A$41,0)),"?") -> ORG | K95: =SUMIFS($H$5:$H$500,$A$5:$A$500,A95)-SUMIFS($I$5:$I$500,$A$5:$A$500,A95) -> 0 | L95: BATCH | M95: stmt:psp:2026-12-16 | N95: =SUMIFS($H$5:H95,$F$5:F95,F95)-SUMIFS($I$5:I95,$F$5:F95,F95) -> 100625
A96: 29 | B96: 46372.375 | C96: Versement PSP | D96: Banque | E96: Versement net CARTE | F96: A-PSP-CARTE | G96: =IFERROR(INDEX('Plan de comptes'!$B$5:$B$41,MATCH(F96,'Plan de comptes'!$A$5:$A$41,0)),"COMPTE INCONNU") -> Créance sur PSP carte | I96: =H95 -> 29250 | J96: =IFERROR(INDEX('Plan de comptes'!$D$5:$D$41,MATCH(F96,'Plan de comptes'!$A$5:$A$41,0)),"?") -> ORG | K96: =SUMIFS($H$5:$H$500,$A$5:$A$500,A96)-SUMIFS($I$5:$I$500,$A$5:$A$500,A96) -> 0 | L96: BATCH | M96: stmt:psp:2026-12-16 | N96: =SUMIFS($H$5:H96,$F$5:F96,F96)-SUMIFS($I$5:I96,$F$5:F96,F96) -> 0
A97: 30 | B97: 46372.5 | C97: Droits de place | D97: Droit de place | E97: Droit de place TTC Food truck | F97: L-MCH-FOOD | G97: =IFERROR(INDEX('Plan de comptes'!$B$5:$B$41,MATCH(F97,'Plan de comptes'!$A$5:$A$41,0)),"COMPTE INCONNU") -> Commerçant externe — Food truck | H97: =Paramètres!$C$15 -> 15000 | J97: =IFERROR(INDEX('Plan de comptes'!$D$5:$D$41,MATCH(F97,'Plan de comptes'!$A$5:$A$41,0)),"?") -> FOOD | K97: =SUMIFS($H$5:$H$500,$A$5:$A$500,A97)-SUMIFS($I$5:$I$500,$A$5:$A$500,A97) -> 0 | L97: BATCH | M97: closing:EVT-2026:place | N97: =SUMIFS($H$5:H97,$F$5:F97,F97)-SUMIFS($I$5:I97,$F$5:F97,F97) -> -11400
A98: 30 | B98: 46372.5 | C98: Droits de place | D98: Droit de place | E98: Droit de place TTC Tee-shirts | F98: L-MCH-TEE | G98: =IFERROR(INDEX('Plan de comptes'!$B$5:$B$41,MATCH(F98,'Plan de comptes'!$A$5:$A$41,0)),"COMPTE INCONNU") -> Commerçant externe — Tee-shirts | H98: =Paramètres!$C$16 -> 10000 | J98: =IFERROR(INDEX('Plan de comptes'!$D$5:$D$41,MATCH(F98,'Plan de comptes'!$A$5:$A$41,0)),"?") -> TEE | K98: =SUMIFS($H$5:$H$500,$A$5:$A$500,A98)-SUMIFS($I$5:$I$500,$A$5:$A$500,A98) -> 0 | L98: BATCH | M98: closing:EVT-2026:place | N98: =SUMIFS($H$5:H98,$F$5:F98,F98)-SUMIFS($I$5:I98,$F$5:F98,F98) -> -8000
A99: 30 | B99: 46372.5 | C99: Droits de place | D99: Droit de place | E99: Droits de place perçus (HT) | F99: L-ORG-PLACE | G99: =IFERROR(INDEX('Plan de comptes'!$B$5:$B$41,MATCH(F99,'Plan de comptes'!$A$5:$A$41,0)),"COMPTE INCONNU") -> Organisateur — droits de place | I99: =(H97+H98)-ROUND((H97+H98)*Paramètres!$C$21/(1+Paramètres!$C$21),0) -> 21186 | J99: =IFERROR(INDEX('Plan de comptes'!$D$5:$D$41,MATCH(F99,'Plan de comptes'!$A$5:$A$41,0)),"?") -> ORG | K99: =SUMIFS($H$5:$H$500,$A$5:$A$500,A99)-SUMIFS($I$5:$I$500,$A$5:$A$500,A99) -> 0 | L99: BATCH | M99: closing:EVT-2026:place | N99: =SUMIFS($H$5:H99,$F$5:F99,F99)-SUMIFS($I$5:I99,$F$5:F99,F99) -> -21186
A100: 30 | B100: 46372.5 | C100: Droits de place | D100: Droit de place | E100: Droits de place perçus (taxe collectée) | F100: L-ORG-TVA | G100: =IFERROR(INDEX('Plan de comptes'!$B$5:$B$41,MATCH(F100,'Plan de comptes'!$A$5:$A$41,0)),"COMPTE INCONNU") -> Organisateur — taxe collectée (à reverser à l'État) | I100: =ROUND((H97+H98)*Paramètres!$C$21/(1+Paramètres!$C$21),0) -> 3814 | J100: =IFERROR(INDEX('Plan de comptes'!$D$5:$D$41,MATCH(F100,'Plan de comptes'!$A$5:$A$41,0)),"?") -> ORG | K100: =SUMIFS($H$5:$H$500,$A$5:$A$500,A100)-SUMIFS($I$5:$I$500,$A$5:$A$500,A100) -> 0 | L100: BATCH | M100: closing:EVT-2026:place | N100: =SUMIFS($H$5:H100,$F$5:F100,F100)-SUMIFS($I$5:I100,$F$5:F100,F100) -> -5432
A101: 31 | B101: 46372.503 | C101: Frais prestataire | D101: Frais prestataire | E101: Frais TTC : % des recharges payées | F101: L-ORG-FPREST | G101: =IFERROR(INDEX('Plan de comptes'!$B$5:$B$41,MATCH(F101,'Plan de comptes'!$A$5:$A$41,0)),"COMPTE INCONNU") -> Organisateur — frais du prestataire | H101: =ROUND(SUMIFS($I$5:$I$100,$C$5:$C$100,"Recharge*",$D$5:$D$100,"Recharge")*Paramètres!$C$17,0) -> 3000 | J101: =IFERROR(INDEX('Plan de comptes'!$D$5:$D$41,MATCH(F101,'Plan de comptes'!$A$5:$A$41,0)),"?") -> ORG | K101: =SUMIFS($H$5:$H$500,$A$5:$A$500,A101)-SUMIFS($I$5:$I$500,$A$5:$A$500,A101) -> 0 | L101: BATCH | M101: closing:EVT-2026:operator-fee | N101: =SUMIFS($H$5:H101,$F$5:F101,F101)-SUMIFS($I$5:I101,$F$5:F101,F101) -> 3000
...

Sheet Grand livre
A1: Grand livre — mouvements regroupés par compte
A2: Chaque ligne renvoie au Journal. Solde cumulé = débits − crédits (positif = débiteur). Disposition figée sur les lignes du scénario ; la Balance, elle, est entièrement dynamique.
A4: Compte / N° tx | B4: Date | C4: Type d'opération | D4: Libellé | E4: Débit | F4: Crédit | G4: Solde cumulé
A5: A-PSP-WAVE | D5: Créance sur Wave
A6: =Journal!A5 -> 1 | B6: =Journal!B5 -> 46357.425 | C6: =Journal!C5 -> Recharge | D6: =Journal!E5 -> Recharge WAVE — Awa (prévente en ligne) | E6: =N(Journal!H5) -> 20000 | F6: =N(Journal!I5) -> 0 | G6: =E6-F6 -> 20000
A7: =Journal!A8 -> 1 | B7: =Journal!B8 -> 46357.425 | C7: =Journal!C8 -> Recharge | D7: =Journal!E8 -> Commission WAVE déduite du versement | E7: =N(Journal!H8) -> 0 | F7: =N(Journal!I8) -> 200 | G7: =G6+E7-F7 -> 19800
A8: =Journal!A92 -> 27 | B8: =Journal!B92 -> 46371.5 | C8: =Journal!C92 -> Versement PSP | D8: =Journal!E92 -> Versement net WAVE | E8: =N(Journal!H92) -> 0 | F8: =N(Journal!I92) -> 19800 | G8: =G7+E8-F8 -> 0
D9: Total A-PSP-WAVE | E9: =SUM(E6:E8) -> 20000 | F9: =SUM(F6:F8) -> 20000 | G9: =E9-F9 -> 0
A11: A-PSP-OM | D11: Créance sur Orange Money
A12: =Journal!A9 -> 2 | B12: =Journal!B9 -> 46367.712 | C12: =Journal!C9 -> Recharge | D12: =Journal!E9 -> Recharge OM — Moussa | E12: =N(Journal!H9) -> 15000 | F12: =N(Journal!I9) -> 0 | G12: =E12-F12 -> 15000
A13: =Journal!A12 -> 2 | B13: =Journal!B12 -> 46367.712 | C13: =Journal!C12 -> Recharge | D13: =Journal!E12 -> Commission OM déduite du versement | E13: =N(Journal!H12) -> 0 | F13: =N(Journal!I12) -> 225 | G13: =G12+E13-F13 -> 14775
A14: =Journal!A94 -> 28 | B14: =Journal!B94 -> 46371.503 | C14: =Journal!C94 -> Versement PSP | D14: =Journal!E94 -> Versement net OM | E14: =N(Journal!H94) -> 0 | F14: =N(Journal!I94) -> 14775 | G14: =G13+E14-F14 -> 0
D15: Total A-PSP-OM | E15: =SUM(E12:E14) -> 15000 | F15: =SUM(F12:F14) -> 15000 | G15: =E15-F15 -> 0
A17: A-PSP-CARTE | D17: Créance sur PSP carte
A18: =Journal!A13 -> 3 | B18: =Journal!B13 -> 46367.736 | C18: =Journal!C13 -> Recharge | D18: =Journal!E13 -> Recharge CARTE — Fatou | E18: =N(Journal!H13) -> 30000 | F18: =N(Journal!I13) -> 0 | G18: =E18-F18 -> 30000
A19: =Journal!A16 -> 3 | B19: =Journal!B16 -> 46367.736 | C19: =Journal!C16 -> Recharge | D19: =Journal!E16 -> Commission CARTE déduite du versement | E19: =N(Journal!H16) -> 0 | F19: =N(Journal!I16) -> 750 | G19: =G18+E19-F19 -> 29250
A20: =Journal!A96 -> 29 | B20: =Journal!B96 -> 46372.375 | C20: =Journal!C96 -> Versement PSP | D20: =Journal!E96 -> Versement net CARTE | E20: =N(Journal!H96) -> 0 | F20: =N(Journal!I96) -> 29250 | G20: =G19+E20-F20 -> 0
D21: Total A-PSP-CARTE | E21: =SUM(E18:E20) -> 30000 | F21: =SUM(F18:F20) -> 30000 | G21: =E21-F21 -> 0
A23: A-CAISSE-C1 | D23: Caisse de recharge C1 (espèces)
A24: =Journal!A17 -> 4 | B24: =Journal!B17 -> 46367.751 | C24: =Journal!C17 -> Recharge espèces | D24: =Journal!E17 -> Recharge espèces caisse C1 — Jean | E24: =N(Journal!H17) -> 10000 | F24: =N(Journal!I17) -> 0 | G24: =E24-F24 -> 10000
A25: =Journal!A19 -> 5 | B25: =Journal!B19 -> 46367.752 | C25: =Journal!C19 -> Caution | D25: =Journal!E19 -> Caution bracelet payée en espèces (mode D) — Jean | E25: =N(Journal!H19) -> 2000 | F25: =N(Journal!I19) -> 0 | G25: =G24+E25-F25 -> 12000
A26: =Journal!A21 -> 6 | B26: =Journal!B21 -> 46367.76 | C26: =Journal!C21 -> Recharge espèces | D26: =Journal!E21 -> Recharge espèces caisse C1 — Aminata | E26: =N(Journal!H21) -> 25000 | F26: =N(Journal!I21) -> 0 | G26: =G25+E26-F26 -> 37000
A27: =Journal!A86 -> 24 | B27: =Journal!B86 -> 46370.042 | C27: =Journal!C86 -> Fermeture caisse | D27: =Journal!E86 -> Solde théorique de la caisse C1 | E27: =N(Journal!H86) -> 0 | F27: =N(Journal!I86) -> 37000 | G27: =G26+E27-F27 -> 0
D28: Total A-CAISSE-C1 | E28: =SUM(E24:E27) -> 37000 | F28: =SUM(F24:F27) -> 37000 | G28: =E28-F28 -> 0
A30: A-TRANSIT | D30: Espèces en transit vers la banque
A31: =Journal!A84 -> 24 | B31: =Journal!B84 -> 46370.042 | C31: =Journal!C84 -> Fermeture caisse | D31: =Journal!E84 -> Espèces comptées, mises en transit | E31: =N(Journal!H84) -> 36800 | F31: =N(Journal!I84) -> 0 | G31: =E31-F31 -> 36800
A32: =Journal!A90 -> 26 | B32: =Journal!B90 -> 46371.375 | C32: =Journal!C90 -> Dépôt espèces | D32: =Journal!E90 -> Dépôt des espèces en banque | E32: =N(Journal!H90) -> 0 | F32: =N(Journal!I90) -> 36800 | G32: =G31+E32-F32 -> 0
D33: Total A-TRANSIT | E33: =SUM(E31:E32) -> 36800 | F33: =SUM(F31:F32) -> 36800 | G33: =E33-F33 -> 0
A35: A-BANQUE | D35: Banque — compte cantonné du pool
A36: =Journal!A89 -> 26 | B36: =Journal!B89 -> 46371.375 | C36: =Journal!C89 -> Dépôt espèces | D36: =Journal!E89 -> Dépôt des espèces en banque | E36: =N(Journal!H89) -> 36800 | F36: =N(Journal!I89) -> 0 | G36: =E36-F36 -> 36800
A37: =Journal!A91 -> 27 | B37: =Journal!B91 -> 46371.5 | C37: =Journal!C91 -> Versement PSP | D37: =Journal!E91 -> Versement net WAVE (rapproché avec le relevé) | E37: =N(Journal!H91) -> 19800 | F37: =N(Journal!I91) -> 0 | G37: =G36+E37-F37 -> 56600
A38: =Journal!A93 -> 28 | B38: =Journal!B93 -> 46371.503 | C38: =Journal!C93 -> Versement PSP | D38: =Journal!E93 -> Versement net OM (rapproché avec le relevé) | E38: =N(Journal!H93) -> 14775 | F38: =N(Journal!I93) -> 0 | G38: =G37+E38-F38 -> 71375
A39: =Journal!A95 -> 29 | B39: =Journal!B95 -> 46372.375 | C39: =Journal!C95 -> Versement PSP | D39: =Journal!E95 -> Versement net CARTE (rapproché avec le relevé) | E39: =N(Journal!H95) -> 29250 | F39: =N(Journal!I95) -> 0 | G39: =G38+E39-F39 -> 100625
A40: =Journal!A115 -> 34 | B40: =Journal!B115 -> 46376.42 | C40: =Journal!C115 -> Versement confirmé | D40: =Journal!E115 -> Versement confirmé — Food truck | E40: =N(Journal!H115) -> 0 | F40: =N(Journal!I115) -> 11400 | G40: =G39+E40-F40 -> 89225
A41: =Journal!A119 -> 36 | B41: =Journal!B119 -> 46376.422 | C41: =Journal!C119 -> Versement confirmé | D41: =Journal!E119 -> Versement confirmé — Bar interne → organisateur | E41: =N(Journal!H119) -> 0 | F41: =N(Journal!I119) -> 18500 | G41: =G40+E41-F41 -> 70725
A42: =Journal!A121 -> 37 | B42: =Journal!B121 -> 46376.422 | C42: =Journal!C121 -> Versement confirmé | D42: =Journal!E121 -> Versement confirmé — Prestataire | E42: =N(Journal!H121) -> 0 | F42: =N(Journal!I121) -> 4983 | G42: =G41+E42-F42 -> 65742
A43: =Journal!A123 -> 38 | B43: =Journal!B123 -> 46376.423 | C43: =Journal!C123 -> Versement confirmé | D43: =Journal!E123 -> Versement confirmé — Plateforme | E43: =N(Journal!H123) -> 0 | F43: =N(Journal!I123) -> 1017 | G43: =G42+E43-F43 -> 64725
A44: =Journal!A127 -> 40 | B44: =Journal!B127 -> 46378.378 | C44: =Journal!C127 -> Versement confirmé | D44: =Journal!E127 -> Versement confirmé — Tee-shirts | E44: =N(Journal!H127) -> 0 | F44: =N(Journal!I127) -> 8000 | G44: =G43+E44-F44 -> 56725
A45: =Journal!A132 -> 41 | B45: =Journal!B132 -> 46378.583 | C45: =Journal!C132 -> Remboursement | D45: =Journal!E132 -> Virement mobile money — Moussa | E45: =N(Journal!H132) -> 0 | F45: =N(Journal!I132) -> 1500 | G45: =G44+E45-F45 -> 55225
A46: =Journal!A137 -> 42 | B46: =Journal!B137 -> 46392.458 | C46: =Journal!C137 -> Remboursement | D46: =Journal!E137 -> Virement mobile money — Fatou | E46: =N(Journal!H137) -> 0 | F46: =N(Journal!I137) -> 12000 | G46: =G45+E46-F46 -> 43225
A47: =Journal!A150 -> 47 | B47: =Journal!B150 -> 46434.42 | C47: =Journal!C150 -> Versement confirmé | D47: =Journal!E150 -> Versement confirmé — organisateur | E47: =N(Journal!H150) -> 0 | F47: =N(Journal!I150) -> 39225 | G47: =G46+E47-F47 -> 4000
A48: =Journal!A152 -> 48 | B48: =Journal!B152 -> 46434.421 | C48: =Journal!C152 -> Versement confirmé | D48: =Journal!E152 -> Versement confirmé — prestataire | E48: =N(Journal!H152) -> 0 | F48: =N(Journal!I152) -> 4000 | G48: =G47+E48-F48 -> 0
D49: Total A-BANQUE | E49: =SUM(E36:E48) -> 100625 | F49: =SUM(F36:F48) -> 100625 | G49: =E49-F49 -> 0
A51: L-WAL-W01-P | D51: Portefeuille W01 Awa — crédits payés
A52: =Journal!A6 -> 1 | B52: =Journal!B6 -> 46357.425 | C52: =Journal!C6 -> Recharge | D52: =Journal!E6 -> Recharge WAVE — Awa (prévente en ligne) | E52: =N(Journal!H6) -> 0 | F52: =N(Journal!I6) -> 20000 | G52: =E52-F52 -> -20000
A53: =Journal!A27 -> 9 | B53: =Journal!B27 -> 46367.771 | C53: =Journal!C27 -> Frais d'activation | D53: =Journal!E27 -> Frais d'activation bracelet W01 | E53: =N(Journal!H27) -> 1000 | F53: =N(Journal!I27) -> 0 | G53: =G52+E53-F53 -> -19000
A54: =Journal!A34 -> 10 | B54: =Journal!B34 -> 46367.799 | C54: =Journal!C34 -> Vente | D54: =Journal!E34 -> Achat FOOD — Awa | E54: =N(Journal!H34) -> 6000 | F54: =N(Journal!I34) -> 0 | G54: =G53+E54-F54 -> -13000
A55: =Journal!A39 -> 11 | B55: =Journal!B39 -> 46367.837 | C55: =Journal!C39 -> Vente | D55: =Journal!E39 -> Achat BAR — Awa | E55: =N(Journal!H39) -> 4000 | F55: =N(Journal!I39) -> 0 | G55: =G54+E55-F55 -> -9000
A56: =Journal!A138 -> 43 | B56: =Journal!B138 -> 46433 | C56: =Journal!C138 -> Casse | D56: =Journal!E138 -> Solde non réclamé à l'échéance — Awa | E56: =N(Journal!H138) -> 9000 | F56: =N(Journal!I138) -> 0 | G56: =G55+E56-F56 -> 0
D57: Total L-WAL-W01-P | E57: =SUM(E52:E56) -> 20000 | F57: =SUM(F52:F56) -> 20000 | G57: =E57-F57 -> 0
A59: L-WAL-W02-P | D59: Portefeuille W02 Moussa — crédits payés
A60: =Journal!A10 -> 2 | B60: =Journal!B10 -> 46367.712 | C60: =Journal!C10 -> Recharge | D60: =Journal!E10 -> Recharge OM — Moussa | E60: =N(Journal!H10) -> 0 | F60: =N(Journal!I10) -> 15000 | G60: =E60-F60 -> -15000
A61: =Journal!A28 -> 9 | B61: =Journal!B28 -> 46367.771 | C61: =Journal!C28 -> Frais d'activation | D61: =Journal!E28 -> Frais d'activation bracelet W02 | E61: =N(Journal!H28) -> 1000 | F61: =N(Journal!I28) -> 0 | G61: =G60+E61-F61 -> -14000
A62: =Journal!A41 -> 12 | B62: =Journal!B41 -> 46367.854 | C62: =Journal!C41 -> Vente | D62: =Journal!E41 -> Achat TEE — Moussa | E62: =N(Journal!H41) -> 12000 | F62: =N(Journal!I41) -> 0 | G62: =G61+E62-F62 -> -2000
A63: =Journal!A128 -> 41 | B63: =Journal!B128 -> 46378.583 | C63: =Journal!C128 -> Remboursement | D63: =Journal!E128 -> Frais de remboursement TTC — Moussa | E63: =N(Journal!H128) -> 500 | F63: =N(Journal!I128) -> 0 | G63: =G62+E63-F63 -> -1500
A64: =Journal!A131 -> 41 | B64: =Journal!B131 -> 46378.583 | C64: =Journal!C131 -> Remboursement | D64: =Journal!E131 -> Remboursement du solde — Moussa | E64: =N(Journal!H131) -> 1500 | F64: =N(Journal!I131) -> 0 | G64: =G63+E64-F64 -> 0
D65: Total L-WAL-W02-P | E65: =SUM(E60:E64) -> 15000 | F65: =SUM(F60:F64) -> 15000 | G65: =E65-F65 -> 0
A67: L-WAL-W03-P | D67: Portefeuille W03 Fatou — crédits payés
A68: =Journal!A14 -> 3 | B68: =Journal!B14 -> 46367.736 | C68: =Journal!C14 -> Recharge | D68: =Journal!E14 -> Recharge CARTE — Fatou | E68: =N(Journal!H14) -> 0 | F68: =N(Journal!I14) -> 30000 | G68: =E68-F68 -> -30000
A69: =Journal!A29 -> 9 | B69: =Journal!B29 -> 46367.771 | C69: =Journal!C29 -> Frais d'activation | D69: =Journal!E29 -> Frais d'activation bracelet W03 | E69: =N(Journal!H29) -> 1000 | F69: =N(Journal!I29) -> 0 | G69: =G68+E69-F69 -> -29000
A70: =Journal!A46 -> 13 | B70: =Journal!B46 -> 46367.875 | C70: =Journal!C46 -> Vente | D70: =Journal!E46 -> Achat FOOD — Fatou | E70: =N(Journal!H46) -> 9000 | F70: =N(Journal!I46) -> 0 | G70: =G69+E70-F70 -> -20000
A71: =Journal!A51 -> 14 | B71: =Journal!B51 -> 46367.927 | C71: =Journal!C51 -> Vente | D71: =Journal!E51 -> Achat BAR — Fatou | E71: =N(Journal!H51) -> 7500 | F71: =N(Journal!I51) -> 0 | G71: =G70+E71-F71 -> -12500
A72: =Journal!A133 -> 42 | B72: =Journal!B133 -> 46392.458 | C72: =Journal!C133 -> Remboursement | D72: =Journal!E133 -> Frais de remboursement TTC — Fatou | E72: =N(Journal!H133) -> 500 | F72: =N(Journal!I133) -> 0 | G72: =G71+E72-F72 -> -12000
A73: =Journal!A136 -> 42 | B73: =Journal!B136 -> 46392.458 | C73: =Journal!C136 -> Remboursement | D73: =Journal!E136 -> Remboursement du solde — Fatou | E73: =N(Journal!H136) -> 12000 | F73: =N(Journal!I136) -> 0 | G73: =G72+E73-F73 -> 0
D74: Total L-WAL-W03-P | E74: =SUM(E68:E73) -> 30000 | F74: =SUM(F68:F73) -> 30000 | G74: =E74-F74 -> 0
A76: L-WAL-W04-P | D76: Portefeuille W04 Jean — crédits payés
A77: =Journal!A18 -> 4 | B77: =Journal!B18 -> 46367.751 | C77: =Journal!C18 -> Recharge espèces | D77: =Journal!E18 -> Recharge espèces caisse C1 — Jean | E77: =N(Journal!H18) -> 0 | F77: =N(Journal!I18) -> 10000 | G77: =E77-F77 -> -10000
A78: =Journal!A30 -> 9 | B78: =Journal!B30 -> 46367.771 | C78: =Journal!C30 -> Frais d'activation | D78: =Journal!E30 -> Frais d'activation bracelet W04 | E78: =N(Journal!H30) -> 1000 | F78: =N(Journal!I30) -> 0 | G78: =G77+E78-F78 -> -9000
A79: =Journal!A53 -> 15 | B79: =Journal!B53 -> 46368.792 | C79: =Journal!C53 -> Vente | D79: =Journal!E53 -> Achat BAR — Jean | E79: =N(Journal!H53) -> 6000 | F79: =N(Journal!I53) -> 0 | G79: =G78+E79-F79 -> -3000
A80: =Journal!A56 -> 16 | B80: =Journal!B56 -> 46368.794 | C80: =Journal!C56 -> Annulation vente | D80: =Journal!E56 -> Contre-passation de T15 (erreur de saisie) | E80: =N(Journal!H56) -> 0 | F80: =N(Journal!I56) -> 6000 | G80: =G79+E80-F80 -> -9000
A81: =Journal!A57 -> 17 | B81: =Journal!B57 -> 46368.794 | C81: =Journal!C57 -> Vente | D81: =Journal!E57 -> Achat BAR — Jean (montant corrigé) | E81: =N(Journal!H57) -> 3000 | F81: =N(Journal!I57) -> 0 | G81: =G80+E81-F81 -> -6000
A82: =Journal!A76 -> 22 | B82: =Journal!B76 -> 46369.896 | C82: =Journal!C76 -> Vente hors ligne | D82: =Journal!E76 -> Achat FOOD hors ligne — Jean (synchro : solde insuffisant) | E82: =N(Journal!H76) -> 6000 | F82: =N(Journal!I76) -> 0 | G82: =G81+E82-F82 -> 0
D83: Total L-WAL-W04-P | E83: =SUM(E77:E82) -> 16000 | F83: =SUM(F77:F82) -> 16000 | G83: =E83-F83 -> 0
A85: L-WAL-W05-P | D85: Portefeuille W05 Aminata — crédits payés
A86: =Journal!A22 -> 6 | B86: =Journal!B22 -> 46367.76 | C86: =Journal!C22 -> Recharge espèces | D86: =Journal!E22 -> Recharge espèces caisse C1 — Aminata | E86: =N(Journal!H22) -> 0 | F86: =N(Journal!I22) -> 25000 | G86: =E86-F86 -> -25000
A87: =Journal!A23 -> 7 | B87: =Journal!B23 -> 46367.761 | C87: =Journal!C23 -> Caution | D87: =Journal!E23 -> Caution prélevée sur le solde (mode C) — Aminata | E87: =N(Journal!H23) -> 2000 | F87: =N(Journal!I23) -> 0 | G87: =G86+E87-F87 -> -23000
A88: =Journal!A31 -> 9 | B88: =Journal!B31 -> 46367.771 | C88: =Journal!C31 -> Frais d'activation | D88: =Journal!E31 -> Frais d'activation bracelet W05 | E88: =N(Journal!H31) -> 1000 | F88: =N(Journal!I31) -> 0 | G88: =G87+E88-F88 -> -22000
A89: =Journal!A59 -> 18 | B89: =Journal!B59 -> 46368.847 | C89: =Journal!C59 -> Vente | D89: =Journal!E59 -> Achat TEE — Aminata | E89: =N(Journal!H59) -> 8000 | F89: =N(Journal!I59) -> 0 | G89: =G88+E89-F89 -> -14000
A90: =Journal!A64 -> 19 | B90: =Journal!B64 -> 46368.906 | C90: =Journal!C64 -> Vente | D90: =Journal!E64 -> Achat FOOD — Aminata | E90: =N(Journal!H64) -> 5000 | F90: =N(Journal!I64) -> 0 | G90: =G89+E90-F90 -> -9000
A91: =Journal!A83 -> 23 | B91: =Journal!B83 -> 46369.979 | C91: =Journal!C83 -> Caution rendue | D91: =Journal!E83 -> Caution recréditée — Aminata | E91: =N(Journal!H83) -> 0 | F91: =N(Journal!I83) -> 2000 | G91: =G90+E91-F91 -> -11000
A92: =Journal!A139 -> 43 | B92: =Journal!B139 -> 46433 | C92: =Journal!C139 -> Casse | D92: =Journal!E139 -> Solde non réclamé à l'échéance — Aminata | E92: =N(Journal!H139) -> 11000 | F92: =N(Journal!I139) -> 0 | G92: =G91+E92-F92 -> 0
D93: Total L-WAL-W05-P | E93: =SUM(E86:E92) -> 27000 | F93: =SUM(F86:F92) -> 27000 | G93: =E93-F93 -> 0
A95: L-WAL-W06-X | D95: Portefeuille W06 Ibou — crédits offerts
A96: =Journal!A26 -> 8 | B96: =Journal!B26 -> 46367.764 | C96: =Journal!C26 -> Crédits offerts | D96: =Journal!E26 -> Crédits staff offerts par l'organisateur — Ibou | E96: =N(Journal!H26) -> 0 | F96: =N(Journal!I26) -> 6000 | G96: =E96-F96 -> -6000
A97: =Journal!A69 -> 20 | B97: =Journal!B69 -> 46368.917 | C97: =Journal!C69 -> Vente | D97: =Journal!E69 -> Achat BAR — Ibou (crédits offerts) | E97: =N(Journal!H69) -> 4000 | F97: =N(Journal!I69) -> 0 | G97: =G96+E97-F97 -> -2000
A98: =Journal!A71 -> 21 | B98: =Journal!B71 -> 46369.542 | C98: =Journal!C71 -> Vente | D98: =Journal!E71 -> Achat FOOD — Ibou (crédits offerts) | E98: =N(Journal!H71) -> 1000 | F98: =N(Journal!I71) -> 0 | G98: =G97+E98-F98 -> -1000
A99: =Journal!A144 -> 45 | B99: =Journal!B144 -> 46433.003 | C99: =Journal!C144 -> Expiration crédits offerts | D99: =Journal!E144 -> Crédits offerts non utilisés — Ibou | E99: =N(Journal!H144) -> 1000 | F99: =N(Journal!I144) -> 0 | G99: =G98+E99-F99 -> 0
D100: Total L-WAL-W06-X | E100: =SUM(E96:E99) -> 6000 | F100: =SUM(F96:F99) -> 6000 | G100: =E100-F100 -> 0
A102: L-MCH-BAR | D102: Commerçant interne — Bar de l'organisateur
A103: =Journal!A40 -> 11 | B103: =Journal!B40 -> 46367.837 | C103: =Journal!C40 -> Vente | D103: =Journal!E40 -> Vente BAR — Awa | E103: =N(Journal!H40) -> 0 | F103: =N(Journal!I40) -> 4000 | G103: =E103-F103 -> -4000
A104: =Journal!A52 -> 14 | B104: =Journal!B52 -> 46367.927 | C104: =Journal!C52 -> Vente | D104: =Journal!E52 -> Vente BAR — Fatou | E104: =N(Journal!H52) -> 0 | F104: =N(Journal!I52) -> 7500 | G104: =G103+E104-F104 -> -11500
A105: =Journal!A54 -> 15 | B105: =Journal!B54 -> 46368.792 | C105: =Journal!C54 -> Vente | D105: =Journal!E54 -> Vente BAR — Jean | E105: =N(Journal!H54) -> 0 | F105: =N(Journal!I54) -> 6000 | G105: =G104+E105-F105 -> -17500
A106: =Journal!A55 -> 16 | B106: =Journal!B55 -> 46368.794 | C106: =Journal!C55 -> Annulation vente | D106: =Journal!E55 -> Contre-passation de T15 (erreur de saisie) | E106: =N(Journal!H55) -> 6000 | F106: =N(Journal!I55) -> 0 | G106: =G105+E106-F106 -> -11500
A107: =Journal!A58 -> 17 | B107: =Journal!B58 -> 46368.794 | C107: =Journal!C58 -> Vente | D107: =Journal!E58 -> Vente BAR — Jean (montant corrigé) | E107: =N(Journal!H58) -> 0 | F107: =N(Journal!I58) -> 3000 | G107: =G106+E107-F107 -> -14500
A108: =Journal!A70 -> 20 | B108: =Journal!B70 -> 46368.917 | C108: =Journal!C70 -> Vente | D108: =Journal!E70 -> Vente BAR — Ibou (crédits offerts) | E108: =N(Journal!H70) -> 0 | F108: =N(Journal!I70) -> 4000 | G108: =G107+E108-F108 -> -18500
A109: =Journal!A110 -> 33 | B109: =Journal!B110 -> 46376.417 | C109: =Journal!C110 -> Versements initiés | D109: =Journal!E110 -> Versement initié — Bar interne → organisateur | E109: =N(Journal!H110) -> 18500 | F109: =N(Journal!I110) -> 0 | G109: =G108+E109-F109 -> 0
D110: Total L-MCH-BAR | E110: =SUM(E103:E109) -> 24500 | F110: =SUM(F103:F109) -> 24500 | G110: =E110-F110 -> 0
A112: L-MCH-FOOD | D112: Commerçant externe — Food truck
A113: =Journal!A35 -> 10 | B113: =Journal!B35 -> 46367.799 | C113: =Journal!C35 -> Vente | D113: =Journal!E35 -> Vente FOOD — Awa | E113: =N(Journal!H35) -> 0 | F113: =N(Journal!I35) -> 6000 | G113: =E113-F113 -> -6000
A114: =Journal!A36 -> 10 | B114: =Journal!B36 -> 46367.799 | C114: =Journal!C36 -> Vente | D114: =Journal!E36 -> Commission TTC sur vente FOOD | E114: =N(Journal!H36) -> 720 | F114: =N(Journal!I36) -> 0 | G114: =G113+E114-F114 -> -5280
...

Sheet Balance
A1: Balance et contrôles
A2: Arrêtée à la transaction n° : | C2: =Paramètres!$C$26 -> 48 | D2: Modifier dans Paramètres (ex. 23 = fin du festival, avant clôture).
A4: Code | B4: Intitulé | C4: Famille | D4: Titulaire | E4: Total débit | F4: Total crédit | G4: Solde (D − C) | H4: Solde débiteur | I4: Solde créditeur | J4: Sens
A5: ='Plan de comptes'!A5 -> A-PSP-WAVE | B5: ='Plan de comptes'!B5 -> Créance sur Wave | C5: ='Plan de comptes'!C5 -> Argent | D5: ='Plan de comptes'!D5 -> ORG | E5: =SUMIFS(Journal!$H$5:$H$500,Journal!$F$5:$F$500,A5,Journal!$A$5:$A$500,"<="&Paramètres!$C$26) -> 20000 | F5: =SUMIFS(Journal!$I$5:$I$500,Journal!$F$5:$F$500,A5,Journal!$A$5:$A$500,"<="&Paramètres!$C$26) -> 20000 | G5: =E5-F5 -> 0 | H5: =MAX(0,G5) -> 0 | I5: =MAX(0,-G5) -> 0 | J5: =IF(AND('Plan de comptes'!F5="Non",OR(AND('Plan de comptes'!E5="D",G5<0),AND('Plan de comptes'!E5="C",G5>0))),"ALERTE","OK") -> OK
A6: ='Plan de comptes'!A6 -> A-PSP-OM | B6: ='Plan de comptes'!B6 -> Créance sur Orange Money | C6: ='Plan de comptes'!C6 -> Argent | D6: ='Plan de comptes'!D6 -> ORG | E6: =SUMIFS(Journal!$H$5:$H$500,Journal!$F$5:$F$500,A6,Journal!$A$5:$A$500,"<="&Paramètres!$C$26) -> 15000 | F6: =SUMIFS(Journal!$I$5:$I$500,Journal!$F$5:$F$500,A6,Journal!$A$5:$A$500,"<="&Paramètres!$C$26) -> 15000 | G6: =E6-F6 -> 0 | H6: =MAX(0,G6) -> 0 | I6: =MAX(0,-G6) -> 0 | J6: =IF(AND('Plan de comptes'!F6="Non",OR(AND('Plan de comptes'!E6="D",G6<0),AND('Plan de comptes'!E6="C",G6>0))),"ALERTE","OK") -> OK
A7: ='Plan de comptes'!A7 -> A-PSP-CARTE | B7: ='Plan de comptes'!B7 -> Créance sur PSP carte | C7: ='Plan de comptes'!C7 -> Argent | D7: ='Plan de comptes'!D7 -> ORG | E7: =SUMIFS(Journal!$H$5:$H$500,Journal!$F$5:$F$500,A7,Journal!$A$5:$A$500,"<="&Paramètres!$C$26) -> 30000 | F7: =SUMIFS(Journal!$I$5:$I$500,Journal!$F$5:$F$500,A7,Journal!$A$5:$A$500,"<="&Paramètres!$C$26) -> 30000 | G7: =E7-F7 -> 0 | H7: =MAX(0,G7) -> 0 | I7: =MAX(0,-G7) -> 0 | J7: =IF(AND('Plan de comptes'!F7="Non",OR(AND('Plan de comptes'!E7="D",G7<0),AND('Plan de comptes'!E7="C",G7>0))),"ALERTE","OK") -> OK
A8: ='Plan de comptes'!A8 -> A-CAISSE-C1 | B8: ='Plan de comptes'!B8 -> Caisse de recharge C1 (espèces) | C8: ='Plan de comptes'!C8 -> Argent | D8: ='Plan de comptes'!D8 -> ORG | E8: =SUMIFS(Journal!$H$5:$H$500,Journal!$F$5:$F$500,A8,Journal!$A$5:$A$500,"<="&Paramètres!$C$26) -> 37000 | F8: =SUMIFS(Journal!$I$5:$I$500,Journal!$F$5:$F$500,A8,Journal!$A$5:$A$500,"<="&Paramètres!$C$26) -> 37000 | G8: =E8-F8 -> 0 | H8: =MAX(0,G8) -> 0 | I8: =MAX(0,-G8) -> 0 | J8: =IF(AND('Plan de comptes'!F8="Non",OR(AND('Plan de comptes'!E8="D",G8<0),AND('Plan de comptes'!E8="C",G8>0))),"ALERTE","OK") -> OK
A9: ='Plan de comptes'!A9 -> A-TRANSIT | B9: ='Plan de comptes'!B9 -> Espèces en transit vers la banque | C9: ='Plan de comptes'!C9 -> Argent | D9: ='Plan de comptes'!D9 -> ORG | E9: =SUMIFS(Journal!$H$5:$H$500,Journal!$F$5:$F$500,A9,Journal!$A$5:$A$500,"<="&Paramètres!$C$26) -> 36800 | F9: =SUMIFS(Journal!$I$5:$I$500,Journal!$F$5:$F$500,A9,Journal!$A$5:$A$500,"<="&Paramètres!$C$26) -> 36800 | G9: =E9-F9 -> 0 | H9: =MAX(0,G9) -> 0 | I9: =MAX(0,-G9) -> 0 | J9: =IF(AND('Plan de comptes'!F9="Non",OR(AND('Plan de comptes'!E9="D",G9<0),AND('Plan de comptes'!E9="C",G9>0))),"ALERTE","OK") -> OK
A10: ='Plan de comptes'!A10 -> A-BANQUE | B10: ='Plan de comptes'!B10 -> Banque — compte cantonné du pool | C10: ='Plan de comptes'!C10 -> Argent | D10: ='Plan de comptes'!D10 -> ORG | E10: =SUMIFS(Journal!$H$5:$H$500,Journal!$F$5:$F$500,A10,Journal!$A$5:$A$500,"<="&Paramètres!$C$26) -> 100625 | F10: =SUMIFS(Journal!$I$5:$I$500,Journal!$F$5:$F$500,A10,Journal!$A$5:$A$500,"<="&Paramètres!$C$26) -> 100625 | G10: =E10-F10 -> 0 | H10: =MAX(0,G10) -> 0 | I10: =MAX(0,-G10) -> 0 | J10: =IF(AND('Plan de comptes'!F10="Non",OR(AND('Plan de comptes'!E10="D",G10<0),AND('Plan de comptes'!E10="C",G10>0))),"ALERTE","OK") -> OK
A11: ='Plan de comptes'!A11 -> L-WAL-W01-P | B11: ='Plan de comptes'!B11 -> Portefeuille W01 Awa — crédits payés | C11: ='Plan de comptes'!C11 -> Droit | D11: ='Plan de comptes'!D11 -> W01 | E11: =SUMIFS(Journal!$H$5:$H$500,Journal!$F$5:$F$500,A11,Journal!$A$5:$A$500,"<="&Paramètres!$C$26) -> 20000 | F11: =SUMIFS(Journal!$I$5:$I$500,Journal!$F$5:$F$500,A11,Journal!$A$5:$A$500,"<="&Paramètres!$C$26) -> 20000 | G11: =E11-F11 -> 0 | H11: =MAX(0,G11) -> 0 | I11: =MAX(0,-G11) -> 0 | J11: =IF(AND('Plan de comptes'!F11="Non",OR(AND('Plan de comptes'!E11="D",G11<0),AND('Plan de comptes'!E11="C",G11>0))),"ALERTE","OK") -> OK
A12: ='Plan de comptes'!A12 -> L-WAL-W02-P | B12: ='Plan de comptes'!B12 -> Portefeuille W02 Moussa — crédits payés | C12: ='Plan de comptes'!C12 -> Droit | D12: ='Plan de comptes'!D12 -> W02 | E12: =SUMIFS(Journal!$H$5:$H$500,Journal!$F$5:$F$500,A12,Journal!$A$5:$A$500,"<="&Paramètres!$C$26) -> 15000 | F12: =SUMIFS(Journal!$I$5:$I$500,Journal!$F$5:$F$500,A12,Journal!$A$5:$A$500,"<="&Paramètres!$C$26) -> 15000 | G12: =E12-F12 -> 0 | H12: =MAX(0,G12) -> 0 | I12: =MAX(0,-G12) -> 0 | J12: =IF(AND('Plan de comptes'!F12="Non",OR(AND('Plan de comptes'!E12="D",G12<0),AND('Plan de comptes'!E12="C",G12>0))),"ALERTE","OK") -> OK
A13: ='Plan de comptes'!A13 -> L-WAL-W03-P | B13: ='Plan de comptes'!B13 -> Portefeuille W03 Fatou — crédits payés | C13: ='Plan de comptes'!C13 -> Droit | D13: ='Plan de comptes'!D13 -> W03 | E13: =SUMIFS(Journal!$H$5:$H$500,Journal!$F$5:$F$500,A13,Journal!$A$5:$A$500,"<="&Paramètres!$C$26) -> 30000 | F13: =SUMIFS(Journal!$I$5:$I$500,Journal!$F$5:$F$500,A13,Journal!$A$5:$A$500,"<="&Paramètres!$C$26) -> 30000 | G13: =E13-F13 -> 0 | H13: =MAX(0,G13) -> 0 | I13: =MAX(0,-G13) -> 0 | J13: =IF(AND('Plan de comptes'!F13="Non",OR(AND('Plan de comptes'!E13="D",G13<0),AND('Plan de comptes'!E13="C",G13>0))),"ALERTE","OK") -> OK
A14: ='Plan de comptes'!A14 -> L-WAL-W04-P | B14: ='Plan de comptes'!B14 -> Portefeuille W04 Jean — crédits payés | C14: ='Plan de comptes'!C14 -> Droit | D14: ='Plan de comptes'!D14 -> W04 | E14: =SUMIFS(Journal!$H$5:$H$500,Journal!$F$5:$F$500,A14,Journal!$A$5:$A$500,"<="&Paramètres!$C$26) -> 16000 | F14: =SUMIFS(Journal!$I$5:$I$500,Journal!$F$5:$F$500,A14,Journal!$A$5:$A$500,"<="&Paramètres!$C$26) -> 16000 | G14: =E14-F14 -> 0 | H14: =MAX(0,G14) -> 0 | I14: =MAX(0,-G14) -> 0 | J14: =IF(AND('Plan de comptes'!F14="Non",OR(AND('Plan de comptes'!E14="D",G14<0),AND('Plan de comptes'!E14="C",G14>0))),"ALERTE","OK") -> OK
A15: ='Plan de comptes'!A15 -> L-WAL-W05-P | B15: ='Plan de comptes'!B15 -> Portefeuille W05 Aminata — crédits payés | C15: ='Plan de comptes'!C15 -> Droit | D15: ='Plan de comptes'!D15 -> W05 | E15: =SUMIFS(Journal!$H$5:$H$500,Journal!$F$5:$F$500,A15,Journal!$A$5:$A$500,"<="&Paramètres!$C$26) -> 27000 | F15: =SUMIFS(Journal!$I$5:$I$500,Journal!$F$5:$F$500,A15,Journal!$A$5:$A$500,"<="&Paramètres!$C$26) -> 27000 | G15: =E15-F15 -> 0 | H15: =MAX(0,G15) -> 0 | I15: =MAX(0,-G15) -> 0 | J15: =IF(AND('Plan de comptes'!F15="Non",OR(AND('Plan de comptes'!E15="D",G15<0),AND('Plan de comptes'!E15="C",G15>0))),"ALERTE","OK") -> OK
A16: ='Plan de comptes'!A16 -> L-WAL-W06-X | B16: ='Plan de comptes'!B16 -> Portefeuille W06 Ibou — crédits offerts | C16: ='Plan de comptes'!C16 -> Droit | D16: ='Plan de comptes'!D16 -> W06 | E16: =SUMIFS(Journal!$H$5:$H$500,Journal!$F$5:$F$500,A16,Journal!$A$5:$A$500,"<="&Paramètres!$C$26) -> 6000 | F16: =SUMIFS(Journal!$I$5:$I$500,Journal!$F$5:$F$500,A16,Journal!$A$5:$A$500,"<="&Paramètres!$C$26) -> 6000 | G16: =E16-F16 -> 0 | H16: =MAX(0,G16) -> 0 | I16: =MAX(0,-G16) -> 0 | J16: =IF(AND('Plan de comptes'!F16="Non",OR(AND('Plan de comptes'!E16="D",G16<0),AND('Plan de comptes'!E16="C",G16>0))),"ALERTE","OK") -> OK
... A41: ='Plan de comptes'!A41 -> S-ATTENTE | B41: ='Plan de comptes'!B41 -> Compte d'attente — anomalies | C41: ='Plan de comptes'!C41 -> Attente | D41: ='Plan de comptes'!D41 -> — | E41: =SUMIFS(Journal!$H$5:$H$500,Journal!$F$5:$F$500,A41,Journal!$A$5:$A$500,"<="&Paramètres!$C$26) -> 3000 | F41: =SUMIFS(Journal!$I$5:$I$500,Journal!$F$5:$F$500,A41,Journal!$A$5:$A$500,"<="&Paramètres!$C$26) -> 3000 | G41: =E41-F41 -> 0 | H41: =MAX(0,G41) -> 0 | I41: =MAX(0,-G41) -> 0 | J41: =IF(AND('Plan de comptes'!F41="Non",OR(AND('Plan de comptes'!E41="D",G41<0),AND('Plan de comptes'!E41="C",G41>0))),"ALERTE","OK") -> OK
B42: Totaux | E42: =SUM(E5:E41) -> 604667 | F42: =SUM(F5:F41) -> 604667 | G42: =SUM(G5:G41) -> 0 | H42: =SUM(H5:H41) -> 65617 | I42: =SUM(I5:I41) -> 65617
A44: Contrôles
A45: Contrôle | E45: Valeur | F45: Attendu | G45: Résultat
A46: Total des débits = total des crédits (écart) | E46: =E42-F42 -> 0 | F46: 0 | G46: =IF(E46=0,"OK","ERREUR") -> OK
A47: Nombre de lignes de transactions déséquilibrées | E47: =COUNTIF(Journal!K5:K152,"<>0") -> 0 | F47: 0 | G47: =IF(E47=0,"OK","ERREUR") -> OK
A48: Argent détenu (comptes Argent) | E48: =SUMIFS(G5:G41,C5:C41,"Argent") -> 0 | F48: — | G48: Info
A49: Droits sur le pool (comptes Droit + Attente) | E49: =-SUMIFS(G5:G41,C5:C41,"<>Argent") -> 0 | F49: — | G49: Info
A50: Écart argent − droits | E50: =E48-E49 -> 0 | F50: 0 | G50: =IF(E50=0,"OK","ERREUR") -> OK
A51: Comptes du mauvais côté (négatif interdit) | E51: =COUNTIF(J5:J41,"ALERTE") -> 0 | F51: 0 | G51: =IF(E51=0,"OK","ERREUR") -> OK
A52: Solde du compte d'attente | E52: =SUMIFS(G5:G41,A5:A41,"S-ATTENTE") -> 0 | F52: 0 à la clôture | G52: =IF(E52=0,"OK","À surveiller") -> OK
A53: Comptes inconnus dans le journal | E53: =COUNTIF(Journal!G5:G152,"COMPTE INCONNU") -> 0 | F53: 0 | G53: =IF(E53=0,"OK","ERREUR") -> OK
A54: Argent restant dans le pool | E54: =SUMIFS(G5:G41,C5:C41,"Argent") -> 0 | F54: 0 si tout est clôturé | G54: =IF(E54=0,"OK","À surveiller") -> OK
A55: Portefeuilles non soldés (droits des festivaliers) | E55: =-SUMIFS(G5:G41,A5:A41,"L-WAL-*") -> 0 | F55: 0 si tout est clôturé | G55: =IF(E55=0,"OK","À surveiller") -> OK
A56: Versements initiés non confirmés | E56: =-SUMIFS(G5:G41,A5:A41,"L-VERS-ENCOURS") -> 0 | F56: 0 quand tout est confirmé | G56: =IF(E56=0,"OK","À surveiller") -> OK
A57: Lignes dont la clé d'idempotence sert à une autre transaction | E57: =SUMPRODUCT((Journal!M5:M152<>"")*(COUNTIFS(Journal!M5:M152,Journal!M5:M152,Journal!A5:A152,"<>"&Journal!A5:A152)>0)) -> 0 | F57: 0 | G57: =IF(E57=0,"OK","ERREUR") -> OK
A59: Droit net de chaque partie sur le pool
A60: Partie | D60: Titulaire | E60: Droit net (XOF)
A61: Festivaliers (tous les portefeuilles) | D61: W* | E61: =-SUMIFS($G$5:$G$41,$D$5:$D$41,D61,$C$5:$C$41,"<>Argent") -> 0
A62: Food truck | D62: FOOD | E62: =-SUMIFS($G$5:$G$41,$D$5:$D$41,D62,$C$5:$C$41,"<>Argent") -> 0
A63: Tee-shirts | D63: TEE | E63: =-SUMIFS($G$5:$G$41,$D$5:$D$41,D63,$C$5:$C$41,"<>Argent") -> 0
A64: Bar interne | D64: BAR | E64: =-SUMIFS($G$5:$G$41,$D$5:$D$41,D64,$C$5:$C$41,"<>Argent") -> 0
A65: Organisateur (somme des L-ORG-*) | D65: ORG | E65: =-SUMIFS($G$5:$G$41,$D$5:$D$41,D65,$C$5:$C$41,"<>Argent") -> 0
A66: Prestataire (somme des L-OPE-*) | D66: OPE | E66: =-SUMIFS($G$5:$G$41,$D$5:$D$41,D66,$C$5:$C$41,"<>Argent") -> 0
A67: Plateforme (somme des L-PLT-*) | D67: PLT | E67: =-SUMIFS($G$5:$G$41,$D$5:$D$41,D67,$C$5:$C$41,"<>Argent") -> 0
A68: Versements en cours et compte d'attente | D68: — | E68: =-SUMIFS($G$5:$G$41,$D$5:$D$41,D68,$C$5:$C$41,"<>Argent") -> 0
A69: Total des droits (doit égaler l'argent détenu) | E69: =SUM(E61:E68) -> 0 | F69: =IF(E69=SUMIFS($G$5:$G$41,$C$5:$C$41,"Argent"),"OK","ERREUR") -> OK

Sheet Relevés
A1: Relevés par partie (arrêtés à la même transaction que la Balance)
A2: Calculés à partir du Journal par nature de ligne. Solde = ce que le pool doit encore à la partie.
A4: A. Commerçants
A5: Ligne | B5: Food truck (externe) | C5: Tee-shirts (externe) | D5: Bar (interne)
A6: Compte | B6: L-MCH-FOOD | C6: L-MCH-TEE | D6: L-MCH-BAR
A7: Ventes brutes | B7: =SUMIFS(Journal!$I$5:$I$500,Journal!$F$5:$F$500,B$6,Journal!$A$5:$A$500,"<="&Paramètres!$C$26,Journal!$D$5:$D$500,"Vente") -> 30000 | C7: =SUMIFS(Journal!$I$5:$I$500,Journal!$F$5:$F$500,C$6,Journal!$A$5:$A$500,"<="&Paramètres!$C$26,Journal!$D$5:$D$500,"Vente") -> 20000 | D7: =SUMIFS(Journal!$I$5:$I$500,Journal!$F$5:$F$500,D$6,Journal!$A$5:$A$500,"<="&Paramètres!$C$26,Journal!$D$5:$D$500,"Vente") -> 24500
A8: Annulations | B8: =-SUMIFS(Journal!$H$5:$H$500,Journal!$F$5:$F$500,B$6,Journal!$A$5:$A$500,"<="&Paramètres!$C$26,Journal!$D$5:$D$500,"Annulation") -> 0 | C8: =-SUMIFS(Journal!$H$5:$H$500,Journal!$F$5:$F$500,C$6,Journal!$A$5:$A$500,"<="&Paramètres!$C$26,Journal!$D$5:$D$500,"Annulation") -> 0 | D8: =-SUMIFS(Journal!$H$5:$H$500,Journal!$F$5:$F$500,D$6,Journal!$A$5:$A$500,"<="&Paramètres!$C$26,Journal!$D$5:$D$500,"Annulation") -> -6000
A9: Commissions | B9: =-SUMIFS(Journal!$H$5:$H$500,Journal!$F$5:$F$500,B$6,Journal!$A$5:$A$500,"<="&Paramètres!$C$26,Journal!$D$5:$D$500,"Commission") -> -3600 | C9: =-SUMIFS(Journal!$H$5:$H$500,Journal!$F$5:$F$500,C$6,Journal!$A$5:$A$500,"<="&Paramètres!$C$26,Journal!$D$5:$D$500,"Commission") -> -2000 | D9: =-SUMIFS(Journal!$H$5:$H$500,Journal!$F$5:$F$500,D$6,Journal!$A$5:$A$500,"<="&Paramètres!$C$26,Journal!$D$5:$D$500,"Commission") -> 0
A10: Droit de place | B10: =-SUMIFS(Journal!$H$5:$H$500,Journal!$F$5:$F$500,B$6,Journal!$A$5:$A$500,"<="&Paramètres!$C$26,Journal!$D$5:$D$500,"Droit de place") -> -15000 | C10: =-SUMIFS(Journal!$H$5:$H$500,Journal!$F$5:$F$500,C$6,Journal!$A$5:$A$500,"<="&Paramètres!$C$26,Journal!$D$5:$D$500,"Droit de place") -> -10000 | D10: =-SUMIFS(Journal!$H$5:$H$500,Journal!$F$5:$F$500,D$6,Journal!$A$5:$A$500,"<="&Paramètres!$C$26,Journal!$D$5:$D$500,"Droit de place") -> 0
A11: Versements initiés | B11: =-SUMIFS(Journal!$H$5:$H$500,Journal!$F$5:$F$500,B$6,Journal!$A$5:$A$500,"<="&Paramètres!$C$26,Journal!$D$5:$D$500,"Versement") -> -11400 | C11: =-SUMIFS(Journal!$H$5:$H$500,Journal!$F$5:$F$500,C$6,Journal!$A$5:$A$500,"<="&Paramètres!$C$26,Journal!$D$5:$D$500,"Versement") -> -16000 | D11: =-SUMIFS(Journal!$H$5:$H$500,Journal!$F$5:$F$500,D$6,Journal!$A$5:$A$500,"<="&Paramètres!$C$26,Journal!$D$5:$D$500,"Versement") -> -18500
A12: Versements échoués (recrédités) | B12: =SUMIFS(Journal!$I$5:$I$500,Journal!$F$5:$F$500,B$6,Journal!$A$5:$A$500,"<="&Paramètres!$C$26,Journal!$D$5:$D$500,"Versement échoué") -> 0 | C12: =SUMIFS(Journal!$I$5:$I$500,Journal!$F$5:$F$500,C$6,Journal!$A$5:$A$500,"<="&Paramètres!$C$26,Journal!$D$5:$D$500,"Versement échoué") -> 8000 | D12: =SUMIFS(Journal!$I$5:$I$500,Journal!$F$5:$F$500,D$6,Journal!$A$5:$A$500,"<="&Paramètres!$C$26,Journal!$D$5:$D$500,"Versement échoué") -> 0
A13: Solde dû au commerçant | B13: =SUM(B7:B12) -> 0 | C13: =SUM(C7:C12) -> 0 | D13: =SUM(D7:D12) -> 0
A14: Contrôle : égal au solde de la Balance | B14: =IF(B13=-SUMIFS(Balance!$G$5:$G$41,Balance!$A$5:$A$41,B$6),"OK","ÉCART") -> OK | C14: =IF(C13=-SUMIFS(Balance!$G$5:$G$41,Balance!$A$5:$A$41,C$6),"OK","ÉCART") -> OK | D14: =IF(D13=-SUMIFS(Balance!$G$5:$G$41,Balance!$A$5:$A$41,D$6),"OK","ÉCART") -> OK
A16: B. Festivaliers
A17: Ligne | B17: W01 Awa | C17: W02 Moussa | D17: W03 Fatou | E17: W04 Jean | F17: W05 Aminata | G17: W06 Ibou (offerts)
A18: Compte | B18: L-WAL-W01-P | C18: L-WAL-W02-P | D18: L-WAL-W03-P | E18: L-WAL-W04-P | F18: L-WAL-W05-P | G18: L-WAL-W06-X
A19: Recharges | B19: =SUMIFS(Journal!$I$5:$I$500,Journal!$F$5:$F$500,B$18,Journal!$A$5:$A$500,"<="&Paramètres!$C$26,Journal!$D$5:$D$500,"Recharge") -> 20000 | C19: =SUMIFS(Journal!$I$5:$I$500,Journal!$F$5:$F$500,C$18,Journal!$A$5:$A$500,"<="&Paramètres!$C$26,Journal!$D$5:$D$500,"Recharge") -> 15000 | D19: =SUMIFS(Journal!$I$5:$I$500,Journal!$F$5:$F$500,D$18,Journal!$A$5:$A$500,"<="&Paramètres!$C$26,Journal!$D$5:$D$500,"Recharge") -> 30000 | E19: =SUMIFS(Journal!$I$5:$I$500,Journal!$F$5:$F$500,E$18,Journal!$A$5:$A$500,"<="&Paramètres!$C$26,Journal!$D$5:$D$500,"Recharge") -> 10000 | F19: =SUMIFS(Journal!$I$5:$I$500,Journal!$F$5:$F$500,F$18,Journal!$A$5:$A$500,"<="&Paramètres!$C$26,Journal!$D$5:$D$500,"Recharge") -> 25000 | G19: =SUMIFS(Journal!$I$5:$I$500,Journal!$F$5:$F$500,G$18,Journal!$A$5:$A$500,"<="&Paramètres!$C$26,Journal!$D$5:$D$500,"Recharge") -> 0
A20: Crédits offerts | B20: =SUMIFS(Journal!$I$5:$I$500,Journal!$F$5:$F$500,B$18,Journal!$A$5:$A$500,"<="&Paramètres!$C$26,Journal!$D$5:$D$500,"Crédit offert") -> 0 | C20: =SUMIFS(Journal!$I$5:$I$500,Journal!$F$5:$F$500,C$18,Journal!$A$5:$A$500,"<="&Paramètres!$C$26,Journal!$D$5:$D$500,"Crédit offert") -> 0 | D20: =SUMIFS(Journal!$I$5:$I$500,Journal!$F$5:$F$500,D$18,Journal!$A$5:$A$500,"<="&Paramètres!$C$26,Journal!$D$5:$D$500,"Crédit offert") -> 0 | E20: =SUMIFS(Journal!$I$5:$I$500,Journal!$F$5:$F$500,E$18,Journal!$A$5:$A$500,"<="&Paramètres!$C$26,Journal!$D$5:$D$500,"Crédit offert") -> 0 | F20: =SUMIFS(Journal!$I$5:$I$500,Journal!$F$5:$F$500,F$18,Journal!$A$5:$A$500,"<="&Paramètres!$C$26,Journal!$D$5:$D$500,"Crédit offert") -> 0 | G20: =SUMIFS(Journal!$I$5:$I$500,Journal!$F$5:$F$500,G$18,Journal!$A$5:$A$500,"<="&Paramètres!$C$26,Journal!$D$5:$D$500,"Crédit offert") -> 6000
A21: Annulations recréditées | B21: =SUMIFS(Journal!$I$5:$I$500,Journal!$F$5:$F$500,B$18,Journal!$A$5:$A$500,"<="&Paramètres!$C$26,Journal!$D$5:$D$500,"Annulation") -> 0 | C21: =SUMIFS(Journal!$I$5:$I$500,Journal!$F$5:$F$500,C$18,Journal!$A$5:$A$500,"<="&Paramètres!$C$26,Journal!$D$5:$D$500,"Annulation") -> 0 | D21: =SUMIFS(Journal!$I$5:$I$500,Journal!$F$5:$F$500,D$18,Journal!$A$5:$A$500,"<="&Paramètres!$C$26,Journal!$D$5:$D$500,"Annulation") -> 0 | E21: =SUMIFS(Journal!$I$5:$I$500,Journal!$F$5:$F$500,E$18,Journal!$A$5:$A$500,"<="&Paramètres!$C$26,Journal!$D$5:$D$500,"Annulation") -> 6000 | F21: =SUMIFS(Journal!$I$5:$I$500,Journal!$F$5:$F$500,F$18,Journal!$A$5:$A$500,"<="&Paramètres!$C$26,Journal!$D$5:$D$500,"Annulation") -> 0 | G21: =SUMIFS(Journal!$I$5:$I$500,Journal!$F$5:$F$500,G$18,Journal!$A$5:$A$500,"<="&Paramètres!$C$26,Journal!$D$5:$D$500,"Annulation") -> 0
A22: Frais (activation, remboursement) | B22: =-SUMIFS(Journal!$H$5:$H$500,Journal!$F$5:$F$500,B$18,Journal!$A$5:$A$500,"<="&Paramètres!$C$26,Journal!$D$5:$D$500,"Frais festivalier") -> -1000 | C22: =-SUMIFS(Journal!$H$5:$H$500,Journal!$F$5:$F$500,C$18,Journal!$A$5:$A$500,"<="&Paramètres!$C$26,Journal!$D$5:$D$500,"Frais festivalier") -> -1500 | D22: =-SUMIFS(Journal!$H$5:$H$500,Journal!$F$5:$F$500,D$18,Journal!$A$5:$A$500,"<="&Paramètres!$C$26,Journal!$D$5:$D$500,"Frais festivalier") -> -1500 | E22: =-SUMIFS(Journal!$H$5:$H$500,Journal!$F$5:$F$500,E$18,Journal!$A$5:$A$500,"<="&Paramètres!$C$26,Journal!$D$5:$D$500,"Frais festivalier") -> -1000 | F22: =-SUMIFS(Journal!$H$5:$H$500,Journal!$F$5:$F$500,F$18,Journal!$A$5:$A$500,"<="&Paramètres!$C$26,Journal!$D$5:$D$500,"Frais festivalier") -> -1000 | G22: =-SUMIFS(Journal!$H$5:$H$500,Journal!$F$5:$F$500,G$18,Journal!$A$5:$A$500,"<="&Paramètres!$C$26,Journal!$D$5:$D$500,"Frais festivalier") -> 0
A23: Achats | B23: =-SUMIFS(Journal!$H$5:$H$500,Journal!$F$5:$F$500,B$18,Journal!$A$5:$A$500,"<="&Paramètres!$C$26,Journal!$D$5:$D$500,"Vente") -> -10000 | C23: =-SUMIFS(Journal!$H$5:$H$500,Journal!$F$5:$F$500,C$18,Journal!$A$5:$A$500,"<="&Paramètres!$C$26,Journal!$D$5:$D$500,"Vente") -> -12000 | D23: =-SUMIFS(Journal!$H$5:$H$500,Journal!$F$5:$F$500,D$18,Journal!$A$5:$A$500,"<="&Paramètres!$C$26,Journal!$D$5:$D$500,"Vente") -> -16500 | E23: =-SUMIFS(Journal!$H$5:$H$500,Journal!$F$5:$F$500,E$18,Journal!$A$5:$A$500,"<="&Paramètres!$C$26,Journal!$D$5:$D$500,"Vente") -> -15000 | F23: =-SUMIFS(Journal!$H$5:$H$500,Journal!$F$5:$F$500,F$18,Journal!$A$5:$A$500,"<="&Paramètres!$C$26,Journal!$D$5:$D$500,"Vente") -> -13000 | G23: =-SUMIFS(Journal!$H$5:$H$500,Journal!$F$5:$F$500,G$18,Journal!$A$5:$A$500,"<="&Paramètres!$C$26,Journal!$D$5:$D$500,"Vente") -> -5000
A24: Caution prélevée (mode C) | B24: =-SUMIFS(Journal!$H$5:$H$500,Journal!$F$5:$F$500,B$18,Journal!$A$5:$A$500,"<="&Paramètres!$C$26,Journal!$D$5:$D$500,"Caution") -> 0 | C24: =-SUMIFS(Journal!$H$5:$H$500,Journal!$F$5:$F$500,C$18,Journal!$A$5:$A$500,"<="&Paramètres!$C$26,Journal!$D$5:$D$500,"Caution") -> 0 | D24: =-SUMIFS(Journal!$H$5:$H$500,Journal!$F$5:$F$500,D$18,Journal!$A$5:$A$500,"<="&Paramètres!$C$26,Journal!$D$5:$D$500,"Caution") -> 0 | E24: =-SUMIFS(Journal!$H$5:$H$500,Journal!$F$5:$F$500,E$18,Journal!$A$5:$A$500,"<="&Paramètres!$C$26,Journal!$D$5:$D$500,"Caution") -> 0 | F24: =-SUMIFS(Journal!$H$5:$H$500,Journal!$F$5:$F$500,F$18,Journal!$A$5:$A$500,"<="&Paramètres!$C$26,Journal!$D$5:$D$500,"Caution") -> -2000 | G24: =-SUMIFS(Journal!$H$5:$H$500,Journal!$F$5:$F$500,G$18,Journal!$A$5:$A$500,"<="&Paramètres!$C$26,Journal!$D$5:$D$500,"Caution") -> 0
A25: Caution rendue (mode C) | B25: =SUMIFS(Journal!$I$5:$I$500,Journal!$F$5:$F$500,B$18,Journal!$A$5:$A$500,"<="&Paramètres!$C$26,Journal!$D$5:$D$500,"Caution") -> 0 | C25: =SUMIFS(Journal!$I$5:$I$500,Journal!$F$5:$F$500,C$18,Journal!$A$5:$A$500,"<="&Paramètres!$C$26,Journal!$D$5:$D$500,"Caution") -> 0 | D25: =SUMIFS(Journal!$I$5:$I$500,Journal!$F$5:$F$500,D$18,Journal!$A$5:$A$500,"<="&Paramètres!$C$26,Journal!$D$5:$D$500,"Caution") -> 0 | E25: =SUMIFS(Journal!$I$5:$I$500,Journal!$F$5:$F$500,E$18,Journal!$A$5:$A$500,"<="&Paramètres!$C$26,Journal!$D$5:$D$500,"Caution") -> 0 | F25: =SUMIFS(Journal!$I$5:$I$500,Journal!$F$5:$F$500,F$18,Journal!$A$5:$A$500,"<="&Paramètres!$C$26,Journal!$D$5:$D$500,"Caution") -> 2000 | G25: =SUMIFS(Journal!$I$5:$I$500,Journal!$F$5:$F$500,G$18,Journal!$A$5:$A$500,"<="&Paramètres!$C$26,Journal!$D$5:$D$500,"Caution") -> 0
A26: Remboursé | B26: =-SUMIFS(Journal!$H$5:$H$500,Journal!$F$5:$F$500,B$18,Journal!$A$5:$A$500,"<="&Paramètres!$C$26,Journal!$D$5:$D$500,"Remboursement") -> 0 | C26: =-SUMIFS(Journal!$H$5:$H$500,Journal!$F$5:$F$500,C$18,Journal!$A$5:$A$500,"<="&Paramètres!$C$26,Journal!$D$5:$D$500,"Remboursement") -> -1500 | D26: =-SUMIFS(Journal!$H$5:$H$500,Journal!$F$5:$F$500,D$18,Journal!$A$5:$A$500,"<="&Paramètres!$C$26,Journal!$D$5:$D$500,"Remboursement") -> -12000 | E26: =-SUMIFS(Journal!$H$5:$H$500,Journal!$F$5:$F$500,E$18,Journal!$A$5:$A$500,"<="&Paramètres!$C$26,Journal!$D$5:$D$500,"Remboursement") -> 0 | F26: =-SUMIFS(Journal!$H$5:$H$500,Journal!$F$5:$F$500,F$18,Journal!$A$5:$A$500,"<="&Paramètres!$C$26,Journal!$D$5:$D$500,"Remboursement") -> 0 | G26: =-SUMIFS(Journal!$H$5:$H$500,Journal!$F$5:$F$500,G$18,Journal!$A$5:$A$500,"<="&Paramètres!$C$26,Journal!$D$5:$D$500,"Remboursement") -> 0
A27: Casse | B27: =-SUMIFS(Journal!$H$5:$H$500,Journal!$F$5:$F$500,B$18,Journal!$A$5:$A$500,"<="&Paramètres!$C$26,Journal!$D$5:$D$500,"Casse") -> -9000 | C27: =-SUMIFS(Journal!$H$5:$H$500,Journal!$F$5:$F$500,C$18,Journal!$A$5:$A$500,"<="&Paramètres!$C$26,Journal!$D$5:$D$500,"Casse") -> 0 | D27: =-SUMIFS(Journal!$H$5:$H$500,Journal!$F$5:$F$500,D$18,Journal!$A$5:$A$500,"<="&Paramètres!$C$26,Journal!$D$5:$D$500,"Casse") -> 0 | E27: =-SUMIFS(Journal!$H$5:$H$500,Journal!$F$5:$F$500,E$18,Journal!$A$5:$A$500,"<="&Paramètres!$C$26,Journal!$D$5:$D$500,"Casse") -> 0 | F27: =-SUMIFS(Journal!$H$5:$H$500,Journal!$F$5:$F$500,F$18,Journal!$A$5:$A$500,"<="&Paramètres!$C$26,Journal!$D$5:$D$500,"Casse") -> -11000 | G27: =-SUMIFS(Journal!$H$5:$H$500,Journal!$F$5:$F$500,G$18,Journal!$A$5:$A$500,"<="&Paramètres!$C$26,Journal!$D$5:$D$500,"Casse") -> 0
A28: Crédits offerts expirés | B28: =-SUMIFS(Journal!$H$5:$H$500,Journal!$F$5:$F$500,B$18,Journal!$A$5:$A$500,"<="&Paramètres!$C$26,Journal!$D$5:$D$500,"Crédit offert") -> 0 | C28: =-SUMIFS(Journal!$H$5:$H$500,Journal!$F$5:$F$500,C$18,Journal!$A$5:$A$500,"<="&Paramètres!$C$26,Journal!$D$5:$D$500,"Crédit offert") -> 0 | D28: =-SUMIFS(Journal!$H$5:$H$500,Journal!$F$5:$F$500,D$18,Journal!$A$5:$A$500,"<="&Paramètres!$C$26,Journal!$D$5:$D$500,"Crédit offert") -> 0 | E28: =-SUMIFS(Journal!$H$5:$H$500,Journal!$F$5:$F$500,E$18,Journal!$A$5:$A$500,"<="&Paramètres!$C$26,Journal!$D$5:$D$500,"Crédit offert") -> 0 | F28: =-SUMIFS(Journal!$H$5:$H$500,Journal!$F$5:$F$500,F$18,Journal!$A$5:$A$500,"<="&Paramètres!$C$26,Journal!$D$5:$D$500,"Crédit offert") -> 0 | G28: =-SUMIFS(Journal!$H$5:$H$500,Journal!$F$5:$F$500,G$18,Journal!$A$5:$A$500,"<="&Paramètres!$C$26,Journal!$D$5:$D$500,"Crédit offert") -> -1000
A29: Solde du portefeuille | B29: =SUM(B19:B28) -> 0 | C29: =SUM(C19:C28) -> 0 | D29: =SUM(D19:D28) -> 0 | E29: =SUM(E19:E28) -> 0 | F29: =SUM(F19:F28) -> 0 | G29: =SUM(G19:G28) -> 0
A30: Contrôle : égal au solde de la Balance | B30: =IF(B29=-SUMIFS(Balance!$G$5:$G$41,Balance!$A$5:$A$41,B$18),"OK","ÉCART") -> OK | C30: =IF(C29=-SUMIFS(Balance!$G$5:$G$41,Balance!$A$5:$A$41,C$18),"OK","ÉCART") -> OK | D30: =IF(D29=-SUMIFS(Balance!$G$5:$G$41,Balance!$A$5:$A$41,D$18),"OK","ÉCART") -> OK | E30: =IF(E29=-SUMIFS(Balance!$G$5:$G$41,Balance!$A$5:$A$41,E$18),"OK","ÉCART") -> OK | F30: =IF(F29=-SUMIFS(Balance!$G$5:$G$41,Balance!$A$5:$A$41,F$18),"OK","ÉCART") -> OK | G30: =IF(G29=-SUMIFS(Balance!$G$5:$G$41,Balance!$A$5:$A$41,G$18),"OK","ÉCART") -> OK
A32: C. Ce que gagne chaque partie
A33: Ligne | B33: Montant (XOF) | C33: Source
A34: Organisateur
A35: Ventes du bar interne (nettes d'annulations) | B35: =SUMIFS(Journal!$I$5:$I$500,Journal!$F$5:$F$500,"L-MCH-BAR",Journal!$A$5:$A$500,"<="&Paramètres!$C$26,Journal!$D$5:$D$500,"Vente")-SUMIFS(Journal!$H$5:$H$500,Journal!$F$5:$F$500,"L-MCH-BAR",Journal!$A$5:$A$500,"<="&Paramètres!$C$26,Journal!$D$5:$D$500,"Annulation") -> 18500 | C35: L-MCH-BAR
A36: Commissions | B36: =-SUMIFS(Balance!$G$5:$G$41,Balance!$A$5:$A$41,"L-ORG-COM") -> 4745 | C36: L-ORG-COM
A37: Droits de place | B37: =-SUMIFS(Balance!$G$5:$G$41,Balance!$A$5:$A$41,"L-ORG-PLACE") -> 21186 | C37: L-ORG-PLACE
A38: Frais festivaliers | B38: =-SUMIFS(Balance!$G$5:$G$41,Balance!$A$5:$A$41,"L-ORG-FFEST") -> 5085 | C38: L-ORG-FFEST
A39: Taxe collectée, à reverser à l'État | B39: =-SUMIFS(Balance!$G$5:$G$41,Balance!$A$5:$A$41,"L-ORG-TVA") -> 5584 | C39: L-ORG-TVA
A40: Casse (part de l'organisateur) | B40: =-SUMIFS(Balance!$G$5:$G$41,Balance!$A$5:$A$41,"L-ORG-CASSE") -> 16000 | C40: L-ORG-CASSE
A41: Cautions détenues, encore à rendre | B41: =-SUMIFS(Balance!$G$5:$G$41,Balance!$A$5:$A$41,"L-ORG-CAUTION") -> 0 | C41: L-ORG-CAUTION
A42: Cautions acquises (bracelets non rendus) | B42: =-SUMIFS(Balance!$G$5:$G$41,Balance!$A$5:$A$41,"L-ORG-CAUTION-ACQ") -> 2000 | C42: L-ORG-CAUTION-ACQ
A43: Crédits offerts consommés | B43: =-SUMIFS(Balance!$G$5:$G$41,Balance!$A$5:$A$41,"L-ORG-PROMO") -> -5000 | C43: L-ORG-PROMO
A44: Frais PSP | B44: =-SUMIFS(Balance!$G$5:$G$41,Balance!$A$5:$A$41,"L-ORG-FPSP") -> -1175 | C44: L-ORG-FPSP
A45: Frais du prestataire | B45: =-SUMIFS(Balance!$G$5:$G$41,Balance!$A$5:$A$41,"L-ORG-FPREST") -> -6000 | C45: L-ORG-FPREST
A46: Pertes (fraude, écart de caisse) | B46: =-SUMIFS(Balance!$G$5:$G$41,Balance!$A$5:$A$41,"L-ORG-PERTES") -> -3200 | C46: L-ORG-PERTES
A47: Droit net de l'organisateur (dont taxe à reverser) | B47: =SUM(B35:B46) -> 57725
A48: Versements initiés | B48: =SUMIFS(Balance!$G$5:$G$41,Balance!$A$5:$A$41,"L-ORG-VERS")+SUMIFS(Journal!$H$5:$H$500,Journal!$F$5:$F$500,"L-MCH-BAR",Journal!$A$5:$A$500,"<="&Paramètres!$C$26,Journal!$D$5:$D$500,"Versement") -> 57725
A49: Reste à verser | B49: =B47-B48 -> 0
A51: Prestataire cashless
A52: Frais facturés (HT) | B52: =-SUMIFS(Balance!$G$5:$G$41,Balance!$A$5:$A$41,"L-OPE-FRAIS") -> 5085 | C52: L-OPE-FRAIS
A53: Taxe collectée, à reverser | B53: =-SUMIFS(Balance!$G$5:$G$41,Balance!$A$5:$A$41,"L-OPE-TVA") -> 915 | C53: L-OPE-TVA
A54: Redevance plateforme | B54: =-SUMIFS(Balance!$G$5:$G$41,Balance!$A$5:$A$41,"L-OPE-REDEV") -> -1017 | C54: L-OPE-REDEV
A55: Part de casse (contrat) | B55: =-SUMIFS(Balance!$G$5:$G$41,Balance!$A$5:$A$41,"L-OPE-CASSE") -> 4000 | C55: L-OPE-CASSE
A56: Droit net du prestataire | B56: =SUM(B52:B55) -> 8983
A57: Versements initiés | B57: =SUMIFS(Balance!$G$5:$G$41,Balance!$A$5:$A$41,"L-OPE-VERS") -> 8983
A58: Reste à verser | B58: =B56-B57 -> 0
A60: Plateforme
A61: Redevance (HT) | B61: =-SUMIFS(Balance!$G$5:$G$41,Balance!$A$5:$A$41,"L-PLT-REDEV") -> 862 | C61: L-PLT-REDEV
A62: Taxe collectée, à reverser | B62: =-SUMIFS(Balance!$G$5:$G$41,Balance!$A$5:$A$41,"L-PLT-TVA") -> 155 | C62: L-PLT-TVA
A63: Droit net de la plateforme | B63: =SUM(B61:B62) -> 1017
A64: Versements initiés | B64: =SUMIFS(Balance!$G$5:$G$41,Balance!$A$5:$A$41,"L-PLT-VERS") -> 1017
A65: Reste à verser | B65: =B63-B64 -> 0

Sheet SYSCOHADA
A1: Correspondance vers la comptabilité légale de l'organisateur (SYSCOHADA révisé)
A2: Numéros INDICATIFS, à valider par un expert-comptable. En base : table account_mapping (entité, purpose, type d'opération → compte légal).
A4: Opération du pool | B4: Débit (organisateur) | C4: Crédit (organisateur) | D4: Remarque
A5: Recharge mobile money / carte | B5: Créance sur PSP (classe 4) ou 585 | C5: 4191 Clients, avances et acomptes reçus | D5: Pas de chiffre d'affaires à la recharge
A6: Recharge espèces | B6: 571 Caisse | C6: 4191
A7: Vente chez un commerçant externe | B7: 4191 | C7: Compte de tiers : fonds à reverser aux commerçants | D7: Pas de chiffre d'affaires pour l'organisateur
A8: Vente au bar interne | B8: 4191 | C8: 701 / 706 Ventes + 443 TVA facturée | D8: Seul cas de vente propre
A9: Commission / droit de place | B9: Compte de tiers commerçant | C9: 706 Services vendus + 443
A10: Frais festivalier | B10: 4191 | C10: 706 + 443
A11: Frais PSP | B11: 631 Frais bancaires | C11: Créance sur PSP
A12: Frais du prestataire | B12: Services extérieurs (classe 6) + 445 TVA récupérable | C12: 401 Fournisseurs | D12: Facture du prestataire
A13: Crédits offerts consommés | B13: Charge selon la nature (classe 6) | C13: 4191 | D13: Communication, personnel…
A14: Pertes hors ligne / écart de caisse | B14: Charges diverses (classe 6) | C14: 4191 / 571
A15: Casse | B15: 4191 | C15: Produit (classe 7) pour la part de l'organisateur ; compte de tiers pour la part du prestataire | D15: Au terme du délai, si la loi le permet ; partage selon le contrat
A16: Caution encaissée (mode C ou D) | B16: 4191 (mode C) ou 571 / créance PSP (mode D) | C16: Dépôts et cautionnements reçus (classe 4) | D16: Ce n'est pas un produit tant que le bracelet peut être rendu
A17: Caution acquise (bracelet non rendu) | B17: Dépôts et cautionnements reçus | C17: Produit (classe 7) | D17: Traitement TVA à confirmer
A18: Taxe collectée sur frais et commissions | B18: (inclus dans le TTC ci-dessus) | C18: 443 État, TVA facturée | D18: Déclarée et reversée par l'organisateur
A19: Versement initié à un commerçant | B19: Compte de tiers commerçant | C19: Versements en cours (compte de tiers transitoire)
A20: Versement confirmé | B20: Versements en cours | C20: 521 Banques | D20: Un échec contre-passe l'écriture d'initiation
A21: Remboursement d'un festivalier | B21: 4191 | C21: 521 Banques
